Workbook

Sheet Trade Tracker - Eval
A1: ZTH | B1: Date | C1: Time | D1: Asset Traded | E1: Direction | F1: Entry Price | G1: Exit Price | H1: Position Size | I1: Stop Loss | J1: Take Profit | K1: RR Targeted | L1: RR Realized | M1: Win/Loss | N1: P&L Amount | O1: P&L % | P1: Cumulative P&L | Q1: Trade Setup | R1: Notes | S1: Intrument Level | T1: Level Screenshot | U1: Trade Screenshot | V1: Mistakes | W1: Rules | X1: Market Conditions | Y1: Emotion Before Trade | Z1: Process | AA1: Learning
A2: 7 | B2: 46251 | C2: 0.41319444 | D2: MNQ | E2: Long | F2: 30240.75 | G2: 30220 | H2: 3 | I2: 30220.75 | J2: 30280.75 | K2: =IF(AND(I2<>"",J2<>"",F2<>""), (J2-F2)/(F2-I2), "") | L2: =IF(AND(F2<>"",G2<>"",I2<>""), (G2-F2)/(F2-I2), "") | M2: =IF(N2>0,"Win",IF(N2<0,"Loss","")) | N2: =IF(AND(F2<>"",G2<>"",H2<>"",D2<>""), IF(E2="Long", (G2-F2)*H2*VLOOKUP(D2,Multipliers!A:B,2,FALSE), (F2-G2)*H2*VLOOKUP(D2,Multipliers!A:B,2,FALSE)), "") | O2: =IF(AND(N2<>"",F2<>"",H2<>"",D2<>""), N2/(F2*H2*VLOOKUP(D2,Multipliers!A:B,2,FALSE)), "") | P2: =N2 | Q2: Break and Retest | S2: MNQ | T2: https://www.tradingview.com/x/ygjyjXNE/ | U2: https://www.tradingview.com/x/pqKL41ZW/ | V2: Cut winner early, Overtraded
A3: 8 | B3: 46251 | C3: 0.42291667 | D3: MGC | E3: Long | F3: 4461.4 | G3: 4473.4 | H3: 2 | I3: 4455.4 | J3: 4473.4 | K3: =IF(AND(I3<>"",J3<>"",F3<>""), (J3-F3)/(F3-I3), "") | L3: =IF(AND(F3<>"",G3<>"",I3<>""), (G3-F3)/(F3-I3), "") | M3: =IF(N3>0,"Win",IF(N3<0,"Loss","")) | N3: =IF(AND(F3<>"",G3<>"",H3<>"",D3<>""), IF(E3="Long", (G3-F3)*H3*VLOOKUP(D3,Multipliers!A:B,2,FALSE), (F3-G3)*H3*VLOOKUP(D3,Multipliers!A:B,2,FALSE)), "") | O3: =IF(AND(N3<>"",F3<>"",H3<>"",D3<>""), N3/(F3*H3*VLOOKUP(D3,Multipliers!A:B,2,FALSE)), "") | P3: =P2+N3 | Q3: Break and Retest | S3: MGC | T3: https://www.tradingview.com/x/soX7jXbm/ | U3: https://www.tradingview.com/x/Hz1BKRjK/ | V3: Oversized, Overtraded
A4: 9 | B4: 46251 | C4: 0.49375 | D4: MNQ | E4: Short | F4: 30237.75 | G4: 30221.5 | H4: 3 | I4: 30257.75 | J4: 30221.5 | K4: =IF(AND(I4<>"",J4<>"",F4<>""), (J4-F4)/(F4-I4), "") | L4: =IF(AND(F4<>"",G4<>"",I4<>""), (G4-F4)/(F4-I4), "") | M4: =IF(N4>0,"Win",IF(N4<0,"Loss","")) | N4: =IF(AND(F4<>"",G4<>"",H4<>"",D4<>""), IF(E4="Long", (G4-F4)*H4*VLOOKUP(D4,Multipliers!A:B,2,FALSE), (F4-G4)*H4*VLOOKUP(D4,Multipliers!A:B,2,FALSE)), "") | O4: =IF(AND(N4<>"",F4<>"",H4<>"",D4<>""), N4/(F4*H4*VLOOKUP(D4,Multipliers!A:B,2,FALSE)), "") | P4: =P3+N4 | Q4: Break and Retest | S4: MNQ | U4: https://www.tradingview.com/x/pqKL41ZW/ | V4: Oversized, Overtraded
A5: 10 | B5: 46245 | C5: 0.81082176 | D5: MGC | E5: Long | F5: 4429.1 | G5: 4430.1 | H5: 3 | I5: 4423.4 | J5: 4431.5 | K5: =IF(AND(I5<>"",J5<>"",F5<>""), (J5-F5)/(F5-I5), "") | L5: =IF(AND(F5<>"",G5<>"",I5<>""), (G5-F5)/(F5-I5), "") | M5: =IF(N5>0,"Win",IF(N5<0,"Loss","")) | N5: =IF(AND(F5<>"",G5<>"",H5<>"",D5<>""), IF(E5="Long", (G5-F5)*H5*VLOOKUP(D5,Multipliers!A:B,2,FALSE), (F5-G5)*H5*VLOOKUP(D5,Multipliers!A:B,2,FALSE)), "") | O5: =IF(AND(N5<>"",F5<>"",H5<>"",D5<>""), N5/(F5*H5*VLOOKUP(D5,Multipliers!A:B,2,FALSE)), "") | P5: =P4+N5 | Q5: Break and Retest | R5: Imported from Tradovate | S5: MGC | V5: Oversized, Revenge trade, Overtraded
A6: 11 | B6: 46245 | C6: 0.81194444 | D6: MGC | E6: Short | F6: 4431.6 | G6: 4430.5 | H6: 10 | J6: 4430.5 | K6: =IF(AND(I6<>"",J6<>"",F6<>""), (J6-F6)/(F6-I6), "") | L6: =IF(AND(F6<>"",G6<>"",I6<>""), (G6-F6)/(F6-I6), "") | M6: =IF(N6>0,"Win",IF(N6<0,"Loss","")) | N6: =IF(AND(F6<>"",G6<>"",H6<>"",D6<>""), IF(E6="Long", (G6-F6)*H6*VLOOKUP(D6,Multipliers!A:B,2,FALSE), (F6-G6)*H6*VLOOKUP(D6,Multipliers!A:B,2,FALSE)), "") | O6: =IF(AND(N6<>"",F6<>"",H6<>"",D6<>""), N6/(F6*H6*VLOOKUP(D6,Multipliers!A:B,2,FALSE)), "") | P6: =P5+N6 | Q6: Break and Retest | R6: Imported from Tradovate | S6: MGC | V6: Oversized, Overtraded
A7: 12 | B7: 46245 | C7: 0.81283565 | D7: MGC | E7: Long | F7: 4430.6 | G7: 4426.2 | H7: 10 | I7: 4423.4 | J7: 4431.5 | K7: =IF(AND(I7<>"",J7<>"",F7<>""), (J7-F7)/(F7-I7), "") | L7: =IF(AND(F7<>"",G7<>"",I7<>""), (G7-F7)/(F7-I7), "") | M7: =IF(N7>0,"Win",IF(N7<0,"Loss","")) | N7: =IF(AND(F7<>"",G7<>"",H7<>"",D7<>""), IF(E7="Long", (G7-F7)*H7*VLOOKUP(D7,Multipliers!A:B,2,FALSE), (F7-G7)*H7*VLOOKUP(D7,Multipliers!A:B,2,FALSE)), "") | O7: =IF(AND(N7<>"",F7<>"",H7<>"",D7<>""), N7/(F7*H7*VLOOKUP(D7,Multipliers!A:B,2,FALSE)), "") | P7: =P6+N7 | Q7: Break and Retest | R7: Imported from Tradovate | S7: MGC | V7: Oversized, Overtraded
A8: 13 | B8: 46245 | C8: 0.81564815 | D8: MGC | E8: Short | F8: 4427 | G8: 4440.1 | H8: 10 | J8: 4426.8 | K8: =IF(AND(I8<>"",J8<>"",F8<>""), (J8-F8)/(F8-I8), "") | L8: =IF(AND(F8<>"",G8<>"",I8<>""), (G8-F8)/(F8-I8), "") | M8: =IF(N8>0,"Win",IF(N8<0,"Loss","")) | N8: =IF(AND(F8<>"",G8<>"",H8<>"",D8<>""), IF(E8="Long", (G8-F8)*H8*VLOOKUP(D8,Multipliers!A:B,2,FALSE), (F8-G8)*H8*VLOOKUP(D8,Multipliers!A:B,2,FALSE)), "") | O8: =IF(AND(N8<>"",F8<>"",H8<>"",D8<>""), N8/(F8*H8*VLOOKUP(D8,Multipliers!A:B,2,FALSE)), "") | P8: =P7+N8 | Q8: Break and Retest | R8: Imported from Tradovate | S8: MGC | V8: Oversized, Overtraded
A9: 14 | B9: 46245 | C9: 0.85517361 | D9: MGC | E9: Long | F9: 4440.1 | G9: 4443.8 | H9: 10 | J9: 4443.8 | K9: =IF(AND(I9<>"",J9<>"",F9<>""), (J9-F9)/(F9-I9), "") | L9: =IF(AND(F9<>"",G9<>"",I9<>""), (G9-F9)/(F9-I9), "") | M9: =IF(N9>0,"Win",IF(N9<0,"Loss","")) | N9: =IF(AND(F9<>"",G9<>"",H9<>"",D9<>""), IF(E9="Long", (G9-F9)*H9*VLOOKUP(D9,Multipliers!A:B,2,FALSE), (F9-G9)*H9*VLOOKUP(D9,Multipliers!A:B,2,FALSE)), "") | O9: =IF(AND(N9<>"",F9<>"",H9<>"",D9<>""), N9/(F9*H9*VLOOKUP(D9,Multipliers!A:B,2,FALSE)), "") | P9: =P8+N9 | Q9: Break and Retest | R9: Imported from Tradovate | S9: MGC | V9: Oversized, Overtraded
A10: 15 | B10: 46245 | C10: 0.88615741 | D10: MGC | E10: Long | F10: 4457.1667 | G10: 4457.8 | H10: 30 | J10: 4472.1 | K10: =IF(AND(I10<>"",J10<>"",F10<>""), (J10-F10)/(F10-I10), "") | L10: =IF(AND(F10<>"",G10<>"",I10<>""), (G10-F10)/(F10-I10), "") | M10: =IF(N10>0,"Win",IF(N10<0,"Loss","")) | N10: =IF(AND(F10<>"",G10<>"",H10<>"",D10<>""), IF(E10="Long", (G10-F10)*H10*VLOOKUP(D10,Multipliers!A:B,2,FALSE), (F10-G10)*H10*VLOOKUP(D10,Multipliers!A:B,2,FALSE)), "") | O10: =IF(AND(N10<>"",F10<>"",H10<>"",D10<>""), N10/(F10*H10*VLOOKUP(D10,Multipliers!A:B,2,FALSE)), "") | P10: =P9+N10 | Q10: Break and Retest | R10: Imported from Tradovate | S10: MGC | V10: Oversized, Overtraded
A11: 16 | B11: 46245 | C11: 0.9446412 | D11: MGC | E11: Long | F11: 4461.8 | G11: 4469 | H11: 30 | J11: 4474.1 | K11: =IF(AND(I11<>"",J11<>"",F11<>""), (J11-F11)/(F11-I11), "") | L11: =IF(AND(F11<>"",G11<>"",I11<>""), (G11-F11)/(F11-I11), "") | M11: =IF(N11>0,"Win",IF(N11<0,"Loss","")) | N11: =IF(AND(F11<>"",G11<>"",H11<>"",D11<>""), IF(E11="Long", (G11-F11)*H11*VLOOKUP(D11,Multipliers!A:B,2,FALSE), (F11-G11)*H11*VLOOKUP(D11,Multipliers!A:B,2,FALSE)), "") | O11: =IF(AND(N11<>"",F11<>"",H11<>"",D11<>""), N11/(F11*H11*VLOOKUP(D11,Multipliers!A:B,2,FALSE)), "") | P11: =P10+N11 | Q11: Break and Retest | R11: Imported from Tradovate | S11: MGC | V11: Oversized, Revenge trade, Overtraded
A12: 17 | B12: 46245 | C12: 0.95865741 | D12: MGC | E12: Long | F12: 4472.3 | G12: 4470.9 | H12: 20 | J12: 4475.9 | K12: =IF(AND(I12<>"",J12<>"",F12<>""), (J12-F12)/(F12-I12), "") | L12: =IF(AND(F12<>"",G12<>"",I12<>""), (G12-F12)/(F12-I12), "") | M12: =IF(N12>0,"Win",IF(N12<0,"Loss","")) | N12: =IF(AND(F12<>"",G12<>"",H12<>"",D12<>""), IF(E12="Long", (G12-F12)*H12*VLOOKUP(D12,Multipliers!A:B,2,FALSE), (F12-G12)*H12*VLOOKUP(D12,Multipliers!A:B,2,FALSE)), "") | O12: =IF(AND(N12<>"",F12<>"",H12<>"",D12<>""), N12/(F12*H12*VLOOKUP(D12,Multipliers!A:B,2,FALSE)), "") | P12: =P11+N12 | Q12: Break and Retest | R12: Imported from Tradovate | S12: MGC | V12: Oversized, Revenge trade, Overtraded
A13: 18 | B13: 46245 | C13: 0.96665509 | D13: MGC | E13: Long | F13: 4473.9 | G13: 4464.8 | H13: 10 | K13: =IF(AND(I13<>"",J13<>"",F13<>""), (J13-F13)/(F13-I13), "") | L13: =IF(AND(F13<>"",G13<>"",I13<>""), (G13-F13)/(F13-I13), "") | M13: =IF(N13>0,"Win",IF(N13<0,"Loss","")) | N13: =IF(AND(F13<>"",G13<>"",H13<>"",D13<>""), IF(E13="Long", (G13-F13)*H13*VLOOKUP(D13,Multipliers!A:B,2,FALSE), (F13-G13)*H13*VLOOKUP(D13,Multipliers!A:B,2,FALSE)), "") | O13: =IF(AND(N13<>"",F13<>"",H13<>"",D13<>""), N13/(F13*H13*VLOOKUP(D13,Multipliers!A:B,2,FALSE)), "") | P13: =P12+N13 | Q13: Break and Retest | R13: Imported from Tradovate | S13: MGC | V13: Overtraded
A14: 19 | B14: 46245 | C14: 0.97626157 | D14: MGC | E14: Long | F14: 4467.3 | G14: 4465.9 | H14: 10 | K14: =IF(AND(I14<>"",J14<>"",F14<>""), (J14-F14)/(F14-I14), "") | L14: =IF(AND(F14<>"",G14<>"",I14<>""), (G14-F14)/(F14-I14), "") | M14: =IF(N14>0,"Win",IF(N14<0,"Loss","")) | N14: =IF(AND(F14<>"",G14<>"",H14<>"",D14<>""), IF(E14="Long", (G14-F14)*H14*VLOOKUP(D14,Multipliers!A:B,2,FALSE), (F14-G14)*H14*VLOOKUP(D14,Multipliers!A:B,2,FALSE)), "") | O14: =IF(AND(N14<>"",F14<>"",H14<>"",D14<>""), N14/(F14*H14*VLOOKUP(D14,Multipliers!A:B,2,FALSE)), "") | P14: =P13+N14 | Q14: Break and Retest | R14: Imported from Tradovate | S14: MGC | V14: Oversized, Overtraded
A15: 20 | B15: 46245 | C15: 0.9837037 | D15: MGC | E15: Short | F15: 4461.05 | G15: 4458.6 | H15: 20 | J15: 4458.6 | K15: =IF(AND(I15<>"",J15<>"",F15<>""), (J15-F15)/(F15-I15), "") | L15: =IF(AND(F15<>"",G15<>"",I15<>""), (G15-F15)/(F15-I15), "") | M15: =IF(N15>0,"Win",IF(N15<0,"Loss","")) | N15: =IF(AND(F15<>"",G15<>"",H15<>"",D15<>""), IF(E15="Long", (G15-F15)*H15*VLOOKUP(D15,Multipliers!A:B,2,FALSE), (F15-G15)*H15*VLOOKUP(D15,Multipliers!A:B,2,FALSE)), "") | O15: =IF(AND(N15<>"",F15<>"",H15<>"",D15<>""), N15/(F15*H15*VLOOKUP(D15,Multipliers!A:B,2,FALSE)), "") | P15: =P14+N15 | Q15: Break and Retest | R15: Imported from Tradovate | S15: MGC | V15: Overtraded
A16: 21 | B16: 46246 | C16: 0.38358796 | D16: MNQ | E16: Long | F16: 29931.25 | G16: 29936 | H16: 5 | J16: 29936 | K16: =IF(AND(I16<>"",J16<>"",F16<>""), (J16-F16)/(F16-I16), "") | L16: =IF(AND(F16<>"",G16<>"",I16<>""), (G16-F16)/(F16-I16), "") | M16: =IF(N16>0,"Win",IF(N16<0,"Loss","")) | N16: =IF(AND(F16<>"",G16<>"",H16<>"",D16<>""), IF(E16="Long", (G16-F16)*H16*VLOOKUP(D16,Multipliers!A:B,2,FALSE), (F16-G16)*H16*VLOOKUP(D16,Multipliers!A:B,2,FALSE)), "") | O16: =IF(AND(N16<>"",F16<>"",H16<>"",D16<>""), N16/(F16*H16*VLOOKUP(D16,Multipliers!A:B,2,FALSE)), "") | P16: =P15+N16 | Q16: Break and Retest | R16: Imported from Tradovate | S16: MNQ | V16: Oversized, Overtraded
A17: 22 | B17: 46246 | C17: 0.39325231 | D17: MGC | E17: Short | F17: 4475.7 | G17: 4474 | H17: 10 | J17: 4474 | K17: =IF(AND(I17<>"",J17<>"",F17<>""), (J17-F17)/(F17-I17), "") | L17: =IF(AND(F17<>"",G17<>"",I17<>""), (G17-F17)/(F17-I17), "") | M17: =IF(N17>0,"Win",IF(N17<0,"Loss","")) | N17: =IF(AND(F17<>"",G17<>"",H17<>"",D17<>""), IF(E17="Long", (G17-F17)*H17*VLOOKUP(D17,Multipliers!A:B,2,FALSE), (F17-G17)*H17*VLOOKUP(D17,Multipliers!A:B,2,FALSE)), "") | O17: =IF(AND(N17<>"",F17<>"",H17<>"",D17<>""), N17/(F17*H17*VLOOKUP(D17,Multipliers!A:B,2,FALSE)), "") | P17: =P16+N17 | Q17: Break and Retest | R17: Imported from Tradovate | S17: MGC | V17: Overtraded
A18: 23 | B18: 46246 | C18: 0.40153935 | D18: MNQ | E18: Short | F18: 29915.75 | G18: 29881 | H18: 1 | J18: 29881 | K18: =IF(AND(I18<>"",J18<>"",F18<>""), (J18-F18)/(F18-I18), "") | L18: =IF(AND(F18<>"",G18<>"",I18<>""), (G18-F18)/(F18-I18), "") | M18: =IF(N18>0,"Win",IF(N18<0,"Loss","")) | N18: =IF(AND(F18<>"",G18<>"",H18<>"",D18<>""), IF(E18="Long", (G18-F18)*H18*VLOOKUP(D18,Multipliers!A:B,2,FALSE), (F18-G18)*H18*VLOOKUP(D18,Multipliers!A:B,2,FALSE)), "") | O18: =IF(AND(N18<>"",F18<>"",H18<>"",D18<>""), N18/(F18*H18*VLOOKUP(D18,Multipliers!A:B,2,FALSE)), "") | P18: =P17+N18 | Q18: Break and Retest | R18: Imported from Tradovate | S18: MNQ | V18: Overtraded
A19: 24 | B19: 46246 | C19: 0.4109838 | D19: MGC | E19: Long | F19: 4490 | G19: 4485.4 | H19: 10 | K19: =IF(AND(I19<>"",J19<>"",F19<>""), (J19-F19)/(F19-I19), "") | L19: =IF(AND(F19<>"",G19<>"",I19<>""), (G19-F19)/(F19-I19), "") | M19: =IF(N19>0,"Win",IF(N19<0,"Loss","")) | N19: =IF(AND(F19<>"",G19<>"",H19<>"",D19<>""), IF(E19="Long", (G19-F19)*H19*VLOOKUP(D19,Multipliers!A:B,2,FALSE), (F19-G19)*H19*VLOOKUP(D19,Multipliers!A:B,2,FALSE)), "") | O19: =IF(AND(N19<>"",F19<>"",H19<>"",D19<>""), N19/(F19*H19*VLOOKUP(D19,Multipliers!A:B,2,FALSE)), "") | P19: =P18+N19 | Q19: Break and Retest | R19: Imported from Tradovate | S19: MGC | V19: Overtraded
A20: 25 | B20: 46246 | C20: 0.45519676 | D20: MNQ | E20: Long | F20: 29863 | G20: 29878.5 | H20: 3 | I20: 29833 | J20: 29878.5 | K20: =IF(AND(I20<>"",J20<>"",F20<>""), (J20-F20)/(F20-I20), "") | L20: =IF(AND(F20<>"",G20<>"",I20<>""), (G20-F20)/(F20-I20), "") | M20: =IF(N20>0,"Win",IF(N20<0,"Loss","")) | N20: =IF(AND(F20<>"",G20<>"",H20<>"",D20<>""), IF(E20="Long", (G20-F20)*H20*VLOOKUP(D20,Multipliers!A:B,2,FALSE), (F20-G20)*H20*VLOOKUP(D20,Multipliers!A:B,2,FALSE)), "") | O20: =IF(AND(N20<>"",F20<>"",H20<>"",D20<>""), N20/(F20*H20*VLOOKUP(D20,Multipliers!A:B,2,FALSE)), "") | P20: =P19+N20 | Q20: Break and Retest | R20: Imported from Tradovate | S20: MNQ | V20: Blew stop, Overtraded
A21: 26 | B21: 46246 | C21: 0.47391204 | D21: MNQ | E21: Long | F21: 29854 | G21: 29879.75 | H21: 3 | I21: 29834.5 | J21: 29894.5 | K21: =IF(AND(I21<>"",J21<>"",F21<>""), (J21-F21)/(F21-I21), "") | L21: =IF(AND(F21<>"",G21<>"",I21<>""), (G21-F21)/(F21-I21), "") | M21: =IF(N21>0,"Win",IF(N21<0,"Loss","")) | N21: =IF(AND(F21<>"",G21<>"",H21<>"",D21<>""), IF(E21="Long", (G21-F21)*H21*VLOOKUP(D21,Multipliers!A:B,2,FALSE), (F21-G21)*H21*VLOOKUP(D21,Multipliers!A:B,2,FALSE)), "") | O21: =IF(AND(N21<>"",F21<>"",H21<>"",D21<>""), N21/(F21*H21*VLOOKUP(D21,Multipliers!A:B,2,FALSE)), "") | P21: =P20+N21 | Q21: Break and Retest | R21: Imported from Tradovate | S21: MNQ | V21: Overtraded
A22: 27 | B22: 46246 | C22: 0.480625 | D22: MNQ | E22: Long | F22: 29855.75 | G22: 29833 | H22: 3 | I22: 29834.5 | J22: 29894.5 | K22: =IF(AND(I22<>"",J22<>"",F22<>""), (J22-F22)/(F22-I22), "") | L22: =IF(AND(F22<>"",G22<>"",I22<>""), (G22-F22)/(F22-I22), "") | M22: =IF(N22>0,"Win",IF(N22<0,"Loss","")) | N22: =IF(AND(F22<>"",G22<>"",H22<>"",D22<>""), IF(E22="Long", (G22-F22)*H22*VLOOKUP(D22,Multipliers!A:B,2,FALSE), (F22-G22)*H22*VLOOKUP(D22,Multipliers!A:B,2,FALSE)), "") | O22: =IF(AND(N22<>"",F22<>"",H22<>"",D22<>""), N22/(F22*H22*VLOOKUP(D22,Multipliers!A:B,2,FALSE)), "") | P22: =P21+N22 | Q22: Break and Retest | R22: Imported from Tradovate | S22: MNQ
A23: 28 | B23: 46246 | C23: 0.49825231 | D23: MNQ | E23: Short | F23: 29838.25 | G23: 29862.25 | H23: 3 | I23: 29858.5 | J23: 29823.5 | K23: =IF(AND(I23<>"",J23<>"",F23<>""), (J23-F23)/(F23-I23), "") | L23: =IF(AND(F23<>"",G23<>"",I23<>""), (G23-F23)/(F23-I23), "") | M23: =IF(N23>0,"Win",IF(N23<0,"Loss","")) | N23: =IF(AND(F23<>"",G23<>"",H23<>"",D23<>""), IF(E23="Long", (G23-F23)*H23*VLOOKUP(D23,Multipliers!A:B,2,FALSE), (F23-G23)*H23*VLOOKUP(D23,Multipliers!A:B,2,FALSE)), "") | O23: =IF(AND(N23<>"",F23<>"",H23<>"",D23<>""), N23/(F23*H23*VLOOKUP(D23,Multipliers!A:B,2,FALSE)), "") | P23: =P22+N23 | Q23: Break and Retest | R23: Imported from Tradovate | S23: MNQ
A24: 29 | B24: 46246 | C24: 0.59178241 | D24: MGC | E24: Short | F24: 4465.4 | G24: 4471.9 | H24: 3 | I24: 4471.8 | J24: 4458.5 | K24: =IF(AND(I24<>"",J24<>"",F24<>""), (J24-F24)/(F24-I24), "") | L24: =IF(AND(F24<>"",G24<>"",I24<>""), (G24-F24)/(F24-I24), "") | M24: =IF(N24>0,"Win",IF(N24<0,"Loss","")) | N24: =IF(AND(F24<>"",G24<>"",H24<>"",D24<>""), IF(E24="Long", (G24-F24)*H24*VLOOKUP(D24,Multipliers!A:B,2,FALSE), (F24-G24)*H24*VLOOKUP(D24,Multipliers!A:B,2,FALSE)), "") | O24: =IF(AND(N24<>"",F24<>"",H24<>"",D24<>""), N24/(F24*H24*VLOOKUP(D24,Multipliers!A:B,2,FALSE)), "") | P24: =P23+N24 | Q24: Break and Retest | R24: Imported from Tradovate | S24: MGC
A25: 30 | B25: 46247 | C25: 0.36866898 | D25: MGC | E25: Long | F25: 4450.95 | G25: 4448.1 | H25: 2 | I25: 4444.4 | J25: 4451.8 | K25: =IF(AND(I25<>"",J25<>"",F25<>""), (J25-F25)/(F25-I25), "") | L25: =IF(AND(F25<>"",G25<>"",I25<>""), (G25-F25)/(F25-I25), "") | M25: =IF(N25>0,"Win",IF(N25<0,"Loss","")) | N25: =IF(AND(F25<>"",G25<>"",H25<>"",D25<>""), IF(E25="Long", (G25-F25)*H25*VLOOKUP(D25,Multipliers!A:B,2,FALSE), (F25-G25)*H25*VLOOKUP(D25,Multipliers!A:B,2,FALSE)), "") | O25: =IF(AND(N25<>"",F25<>"",H25<>"",D25<>""), N25/(F25*H25*VLOOKUP(D25,Multipliers!A:B,2,FALSE)), "") | P25: =P24+N25 | Q25: Break and Retest | R25: Imported from Tradovate | S25: MGC
A26: 31 | B26: 46247 | C26: 0.40733796 | D26: MNQ | E26: Long | F26: 30089.5 | G26: 30127 | H26: 5 | I26: 30067 | J26: 30127 | K26: =IF(AND(I26<>"",J26<>"",F26<>""), (J26-F26)/(F26-I26), "") | L26: =IF(AND(F26<>"",G26<>"",I26<>""), (G26-F26)/(F26-I26), "") | M26: =IF(N26>0,"Win",IF(N26<0,"Loss","")) | N26: =IF(AND(F26<>"",G26<>"",H26<>"",D26<>""), IF(E26="Long", (G26-F26)*H26*VLOOKUP(D26,Multipliers!A:B,2,FALSE), (F26-G26)*H26*VLOOKUP(D26,Multipliers!A:B,2,FALSE)), "") | O26: =IF(AND(N26<>"",F26<>"",H26<>"",D26<>""), N26/(F26*H26*VLOOKUP(D26,Multipliers!A:B,2,FALSE)), "") | P26: =P25+N26 | Q26: Break and Retest | R26: Imported from Tradovate | S26: MNQ | V26: Revenge trade
A27: 32 | B27: 46247 | C27: 0.47510417 | D27: MGC | E27: Short | F27: 4427.5 | G27: 4418 | H27: 3 | J27: 4418 | K27: =IF(AND(I27<>"",J27<>"",F27<>""), (J27-F27)/(F27-I27), "") | L27: =IF(AND(F27<>"",G27<>"",I27<>""), (G27-F27)/(F27-I27), "") | M27: =IF(N27>0,"Win",IF(N27<0,"Loss","")) | N27: =IF(AND(F27<>"",G27<>"",H27<>"",D27<>""), IF(E27="Long", (G27-F27)*H27*VLOOKUP(D27,Multipliers!A:B,2,FALSE), (F27-G27)*H27*VLOOKUP(D27,Multipliers!A:B,2,FALSE)), "") | O27: =IF(AND(N27<>"",F27<>"",H27<>"",D27<>""), N27/(F27*H27*VLOOKUP(D27,Multipliers!A:B,2,FALSE)), "") | P27: =P26+N27 | Q27: Break and Retest | R27: Imported from Tradovate | S27: MGC
A28: 33 | B28: 46247 | C28: 0.95162037 | D28: MGC | E28: Long | F28: 4371.8 | G28: 4369.6 | H28: 3 | K28: =IF(AND(I28<>"",J28<>"",F28<>""), (J28-F28)/(F28-I28), "") | L28: =IF(AND(F28<>"",G28<>"",I28<>""), (G28-F28)/(F28-I28), "") | M28: =IF(N28>0,"Win",IF(N28<0,"Loss","")) | N28: =IF(AND(F28<>"",G28<>"",H28<>"",D28<>""), IF(E28="Long", (G28-F28)*H28*VLOOKUP(D28,Multipliers!A:B,2,FALSE), (F28-G28)*H28*VLOOKUP(D28,Multipliers!A:B,2,FALSE)), "") | O28: =IF(AND(N28<>"",F28<>"",H28<>"",D28<>""), N28/(F28*H28*VLOOKUP(D28,Multipliers!A:B,2,FALSE)), "") | P28: =P27+N28 | Q28: Break and Retest | R28: Imported from Tradovate | S28: MGC
A29: 34 | B29: 46247 | C29: 0.95800926 | D29: MGC | E29: Short | F29: 4370.5 | G29: 4377 | H29: 3 | I29: 4377 | J29: 4369.3 | K29: =IF(AND(I29<>"",J29<>"",F29<>""), (J29-F29)/(F29-I29), "") | L29: =IF(AND(F29<>"",G29<>"",I29<>""), (G29-F29)/(F29-I29), "") | M29: =IF(N29>0,"Win",IF(N29<0,"Loss","")) | N29: =IF(AND(F29<>"",G29<>"",H29<>"",D29<>""), IF(E29="Long", (G29-F29)*H29*VLOOKUP(D29,Multipliers!A:B,2,FALSE), (F29-G29)*H29*VLOOKUP(D29,Multipliers!A:B,2,FALSE)), "") | O29: =IF(AND(N29<>"",F29<>"",H29<>"",D29<>""), N29/(F29*H29*VLOOKUP(D29,Multipliers!A:B,2,FALSE)), "") | P29: =P28+N29 | Q29: Break and Retest | R29: Imported from Tradovate | S29: MGC
A30: 35 | B30: 46248 | C30: 0.40767361 | D30: MNQ | E30: Long | F30: 30233 | G30: 30255.75 | H30: 3 | J30: 30272 | K30: =IF(AND(I30<>"",J30<>"",F30<>""), (J30-F30)/(F30-I30), "") | L30: =IF(AND(F30<>"",G30<>"",I30<>""), (G30-F30)/(F30-I30), "") | M30: =IF(N30>0,"Win",IF(N30<0,"Loss","")) | N30: =IF(AND(F30<>"",G30<>"",H30<>"",D30<>""), IF(E30="Long", (G30-F30)*H30*VLOOKUP(D30,Multipliers!A:B,2,FALSE), (F30-G30)*H30*VLOOKUP(D30,Multipliers!A:B,2,FALSE)), "") | O30: =IF(AND(N30<>"",F30<>"",H30<>"",D30<>""), N30/(F30*H30*VLOOKUP(D30,Multipliers!A:B,2,FALSE)), "") | P30: =P29+N30 | Q30: Break and Retest | R30: Imported from Tradovate | S30: MNQ
A31: 36 | B31: 46248 | C31: 0.41525463 | D31: MNQ | E31: Long | F31: 30221 | G31: 30225.5 | H31: 3 | I31: 30201 | J31: 30225.5 | K31: =IF(AND(I31<>"",J31<>"",F31<>""), (J31-F31)/(F31-I31), "") | L31: =IF(AND(F31<>"",G31<>"",I31<>""), (G31-F31)/(F31-I31), "") | M31: =IF(N31>0,"Win",IF(N31<0,"Loss","")) | N31: =IF(AND(F31<>"",G31<>"",H31<>"",D31<>""), IF(E31="Long", (G31-F31)*H31*VLOOKUP(D31,Multipliers!A:B,2,FALSE), (F31-G31)*H31*VLOOKUP(D31,Multipliers!A:B,2,FALSE)), "") | O31: =IF(AND(N31<>"",F31<>"",H31<>"",D31<>""), N31/(F31*H31*VLOOKUP(D31,Multipliers!A:B,2,FALSE)), "") | P31: =P30+N31 | Q31: Break and Retest | R31: Imported from Tradovate | S31: MNQ
A32: 37 | B32: 46248 | C32: 0.49888889 | D32: MNQ | E32: Short | F32: 30072.5 | G32: 30099.5 | H32: 3 | I32: 30099.5 | J32: 30058.25 | K32: =IF(AND(I32<>"",J32<>"",F32<>""), (J32-F32)/(F32-I32), "") | L32: =IF(AND(F32<>"",G32<>"",I32<>""), (G32-F32)/(F32-I32), "") | M32: =IF(N32>0,"Win",IF(N32<0,"Loss","")) | N32: =IF(AND(F32<>"",G32<>"",H32<>"",D32<>""), IF(E32="Long", (G32-F32)*H32*VLOOKUP(D32,Multipliers!A:B,2,FALSE), (F32-G32)*H32*VLOOKUP(D32,Multipliers!A:B,2,FALSE)), "") | O32: =IF(AND(N32<>"",F32<>"",H32<>"",D32<>""), N32/(F32*H32*VLOOKUP(D32,Multipliers!A:B,2,FALSE)), "") | P32: =P31+N32 | Q32: Break and Retest | R32: Imported from Tradovate | S32: MNQ
A33: 38 | B33: 46248 | C33: 0.5287037 | D33: MNQ | E33: Short | F33: 30068.5 | G33: 30064 | H33: 3 | I33: 30088.5 | J33: 30064 | K33: =IF(AND(I33<>"",J33<>"",F33<>""), (J33-F33)/(F33-I33), "") | L33: =IF(AND(F33<>"",G33<>"",I33<>""), (G33-F33)/(F33-I33), "") | M33: =IF(N33>0,"Win",IF(N33<0,"Loss","")) | N33: =IF(AND(F33<>"",G33<>"",H33<>"",D33<>""), IF(E33="Long", (G33-F33)*H33*VLOOKUP(D33,Multipliers!A:B,2,FALSE), (F33-G33)*H33*VLOOKUP(D33,Multipliers!A:B,2,FALSE)), "") | O33: =IF(AND(N33<>"",F33<>"",H33<>"",D33<>""), N33/(F33*H33*VLOOKUP(D33,Multipliers!A:B,2,FALSE)), "") | P33: =P32+N33 | Q33: Break and Retest | R33: Imported from Tradovate | S33: MNQ
A34: 39 | B34: 46248 | C34: 0.53212963 | D34: MNQ | E34: Long | F34: 30067 | G34: 30071.25 | H34: 5 | I34: 30047.75 | J34: 30074.5 | K34: =IF(AND(I34<>"",J34<>"",F34<>""), (J34-F34)/(F34-I34), "") | L34: =IF(AND(F34<>"",G34<>"",I34<>""), (G34-F34)/(F34-I34), "") | M34: =IF(N34>0,"Win",IF(N34<0,"Loss","")) | N34: =IF(AND(F34<>"",G34<>"",H34<>"",D34<>""), IF(E34="Long", (G34-F34)*H34*VLOOKUP(D34,Multipliers!A:B,2,FALSE), (F34-G34)*H34*VLOOKUP(D34,Multipliers!A:B,2,FALSE)), "") | O34: =IF(AND(N34<>"",F34<>"",H34<>"",D34<>""), N34/(F34*H34*VLOOKUP(D34,Multipliers!A:B,2,FALSE)), "") | P34: =P33+N34 | Q34: Break and Retest | R34: Imported from Tradovate | S34: MNQ
A35: 40 | B35: 46248 | C35: 0.53502315 | D35: MNQ | E35: Long | F35: 30064.5 | G35: 30068 | H35: 5 | J35: 30074.5 | K35: =IF(AND(I35<>"",J35<>"",F35<>""), (J35-F35)/(F35-I35), "") | L35: =IF(AND(F35<>"",G35<>"",I35<>""), (G35-F35)/(F35-I35), "") | M35: =IF(N35>0,"Win",IF(N35<0,"Loss","")) | N35: =IF(AND(F35<>"",G35<>"",H35<>"",D35<>""), IF(E35="Long", (G35-F35)*H35*VLOOKUP(D35,Multipliers!A:B,2,FALSE), (F35-G35)*H35*VLOOKUP(D35,Multipliers!A:B,2,FALSE)), "") | O35: =IF(AND(N35<>"",F35<>"",H35<>"",D35<>""), N35/(F35*H35*VLOOKUP(D35,Multipliers!A:B,2,FALSE)), "") | P35: =P34+N35 | Q35: Break and Retest | R35: Imported from Tradovate | S35: MNQ
A36: 41 | B36: 46252 | C36: 0.41706019 | D36: MGC | E36: Short | F36: 4454.7 | G36: 4460 | H36: 3 | I36: 4459.9 | J36: 4454 | K36: =IF(AND(I36<>"",J36<>"",F36<>""), (J36-F36)/(F36-I36), "") | L36: =IF(AND(F36<>"",G36<>"",I36<>""), (G36-F36)/(F36-I36), "") | M36: =IF(N36>0,"Win",IF(N36<0,"Loss","")) | N36: =IF(AND(F36<>"",G36<>"",H36<>"",D36<>""), IF(E36="Long", (G36-F36)*H36*VLOOKUP(D36,Multipliers!A:B,2,FALSE), (F36-G36)*H36*VLOOKUP(D36,Multipliers!A:B,2,FALSE)), "") | O36: =IF(AND(N36<>"",F36<>"",H36<>"",D36<>""), N36/(F36*H36*VLOOKUP(D36,Multipliers!A:B,2,FALSE)), "") | P36: =P35+N36 | Q36: Break and Retest | R36: Imported from Tradovate | S36: MGC
A37: 42 | B37: 46252 | C37: 0.42253472 | D37: MGC | E37: Long | F37: 4454.2 | G37: 4448.2 | H37: 3 | I37: 4448.2 | J37: 4467 | K37: =IF(AND(I37<>"",J37<>"",F37<>""), (J37-F37)/(F37-I37), "") | L37: =IF(AND(F37<>"",G37<>"",I37<>""), (G37-F37)/(F37-I37), "") | M37: =IF(N37>0,"Win",IF(N37<0,"Loss","")) | N37: =IF(AND(F37<>"",G37<>"",H37<>"",D37<>""), IF(E37="Long", (G37-F37)*H37*VLOOKUP(D37,Multipliers!A:B,2,FALSE), (F37-G37)*H37*VLOOKUP(D37,Multipliers!A:B,2,FALSE)), "") | O37: =IF(AND(N37<>"",F37<>"",H37<>"",D37<>""), N37/(F37*H37*VLOOKUP(D37,Multipliers!A:B,2,FALSE)), "") | P37: =P36+N37 | Q37: Break and Retest | R37: Imported from Tradovate | S37: MGC | V37: Revenge trade
A38: 43 | B38: 46252 | C38: 0.42832176 | D38: MNQ | E38: Short | F38: 29614 | G38: 29634 | H38: 2 | I38: 29634 | J38: 29574 | K38: =IF(AND(I38<>"",J38<>"",F38<>""), (J38-F38)/(F38-I38), "") | L38: =IF(AND(F38<>"",G38<>"",I38<>""), (G38-F38)/(F38-I38), "") | M38: =IF(N38>0,"Win",IF(N38<0,"Loss","")) | N38: =IF(AND(F38<>"",G38<>"",H38<>"",D38<>""), IF(E38="Long", (G38-F38)*H38*VLOOKUP(D38,Multipliers!A:B,2,FALSE), (F38-G38)*H38*VLOOKUP(D38,Multipliers!A:B,2,FALSE)), "") | O38: =IF(AND(N38<>"",F38<>"",H38<>"",D38<>""), N38/(F38*H38*VLOOKUP(D38,Multipliers!A:B,2,FALSE)), "") | P38: =P37+N38 | Q38: Break and Retest | R38: Imported from Tradovate | S38: MNQ
A39: 44 | B39: 46252 | C39: 0.43178241 | D39: MNQ | E39: Short | F39: 29607.5 | G39: 29656.75 | H39: 3 | I39: 29649 | J39: 29552 | K39: =IF(AND(I39<>"",J39<>"",F39<>""), (J39-F39)/(F39-I39), "") | L39: =IF(AND(F39<>"",G39<>"",I39<>""), (G39-F39)/(F39-I39), "") | M39: =IF(N39>0,"Win",IF(N39<0,"Loss","")) | N39: =IF(AND(F39<>"",G39<>"",H39<>"",D39<>""), IF(E39="Long", (G39-F39)*H39*VLOOKUP(D39,Multipliers!A:B,2,FALSE), (F39-G39)*H39*VLOOKUP(D39,Multipliers!A:B,2,FALSE)), "") | O39: =IF(AND(N39<>"",F39<>"",H39<>"",D39<>""), N39/(F39*H39*VLOOKUP(D39,Multipliers!A:B,2,FALSE)), "") | P39: =P38+N39 | Q39: Break and Retest | R39: Imported from Tradovate | S39: MNQ | V39: Blew stop, Revenge trade
A40: 45 | B40: 46252 | C40: 0.45059028 | D40: MGC | E40: Short | F40: 4444.2 | G40: 4434.5 | H40: 2 | I40: 4447.8 | J40: 4434.5 | K40: =IF(AND(I40<>"",J40<>"",F40<>""), (J40-F40)/(F40-I40), "") | L40: =IF(AND(F40<>"",G40<>"",I40<>""), (G40-F40)/(F40-I40), "") | M40: =IF(N40>0,"Win",IF(N40<0,"Loss","")) | N40: =IF(AND(F40<>"",G40<>"",H40<>"",D40<>""), IF(E40="Long", (G40-F40)*H40*VLOOKUP(D40,Multipliers!A:B,2,FALSE), (F40-G40)*H40*VLOOKUP(D40,Multipliers!A:B,2,FALSE)), "") | O40: =IF(AND(N40<>"",F40<>"",H40<>"",D40<>""), N40/(F40*H40*VLOOKUP(D40,Multipliers!A:B,2,FALSE)), "") | P40: =P39+N40 | Q40: Break and Retest | R40: Imported from Tradovate | S40: MGC
A41: 46 | B41: 46253 | C41: 0.40523148 | D41: MNQ | E41: Short | F41: 29615.5 | G41: 29544.25 | H41: 3 | J41: 29549 | K41: =IF(AND(I41<>"",J41<>"",F41<>""), (J41-F41)/(F41-I41), "") | L41: =IF(AND(F41<>"",G41<>"",I41<>""), (G41-F41)/(F41-I41), "") | M41: =IF(N41>0,"Win",IF(N41<0,"Loss","")) | N41: =IF(AND(F41<>"",G41<>"",H41<>"",D41<>""), IF(E41="Long", (G41-F41)*H41*VLOOKUP(D41,Multipliers!A:B,2,FALSE), (F41-G41)*H41*VLOOKUP(D41,Multipliers!A:B,2,FALSE)), "") | O41: =IF(AND(N41<>"",F41<>"",H41<>"",D41<>""), N41/(F41*H41*VLOOKUP(D41,Multipliers!A:B,2,FALSE)), "") | P41: =P40+N41 | Q41: Break and Retest | R41: Imported from Tradovate | S41: MNQ
A42: 47 | B42: 46253 | C42: 0.52335648 | D42: MNQ | E42: Short | F42: 29614.75 | G42: 29607 | H42: 3 | I42: 29638.75 | J42: 29607 | K42: =IF(AND(I42<>"",J42<>"",F42<>""), (J42-F42)/(F42-I42), "") | L42: =IF(AND(F42<>"",G42<>"",I42<>""), (G42-F42)/(F42-I42), "") | M42: =IF(N42>0,"Win",IF(N42<0,"Loss","")) | N42: =IF(AND(F42<>"",G42<>"",H42<>"",D42<>""), IF(E42="Long", (G42-F42)*H42*VLOOKUP(D42,Multipliers!A:B,2,FALSE), (F42-G42)*H42*VLOOKUP(D42,Multipliers!A:B,2,FALSE)), "") | O42: =IF(AND(N42<>"",F42<>"",H42<>"",D42<>""), N42/(F42*H42*VLOOKUP(D42,Multipliers!A:B,2,FALSE)), "") | P42: =P41+N42 | Q42: Break and Retest | R42: Imported from Tradovate | S42: MNQ
A43: 48 | B43: 46253 | C43: 0.60753472 | D43: MGC | E43: Short | F43: 4539.5 | G43: 4546.4 | H43: 3 | I43: 4545.5 | J43: 4537.6 | K43: =IF(AND(I43<>"",J43<>"",F43<>""), (J43-F43)/(F43-I43), "") | L43: =IF(AND(F43<>"",G43<>"",I43<>""), (G43-F43)/(F43-I43), "") | M43: =IF(N43>0,"Win",IF(N43<0,"Loss","")) | N43: =IF(AND(F43<>"",G43<>"",H43<>"",D43<>""), IF(E43="Long", (G43-F43)*H43*VLOOKUP(D43,Multipliers!A:B,2,FALSE), (F43-G43)*H43*VLOOKUP(D43,Multipliers!A:B,2,FALSE)), "") | O43: =IF(AND(N43<>"",F43<>"",H43<>"",D43<>""), N43/(F43*H43*VLOOKUP(D43,Multipliers!A:B,2,FALSE)), "") | P43: =P42+N43 | Q43: Break and Retest | R43: Imported from Tradovate | S43: MGC
A44: 49 | B44: 46253 | C44: 0.62565972 | D44: MNQ | E44: Short | F44: 29544.5 | G44: 29564.5 | H44: 3 | I44: 29564.5 | J44: 29540 | K44: =IF(AND(I44<>"",J44<>"",F44<>""), (J44-F44)/(F44-I44), "") | L44: =IF(AND(F44<>"",G44<>"",I44<>""), (G44-F44)/(F44-I44), "") | M44: =IF(N44>0,"Win",IF(N44<0,"Loss","")) | N44: =IF(AND(F44<>"",G44<>"",H44<>"",D44<>""), IF(E44="Long", (G44-F44)*H44*VLOOKUP(D44,Multipliers!A:B,2,FALSE), (F44-G44)*H44*VLOOKUP(D44,Multipliers!A:B,2,FALSE)), "") | O44: =IF(AND(N44<>"",F44<>"",H44<>"",D44<>""), N44/(F44*H44*VLOOKUP(D44,Multipliers!A:B,2,FALSE)), "") | P44: =P43+N44 | Q44: Break and Retest | R44: Imported from Tradovate | S44: MNQ
A45: 50 | B45: 46254 | C45: 0.41099537 | D45: MGC | E45: Long | F45: 4538.74 | G45: 4551.86 | H45: 5 | I45: 4530.8 | J45: 4555.5 | K45: =IF(AND(I45<>"",J45<>"",F45<>""), (J45-F45)/(F45-I45), "") | L45: =IF(AND(F45<>"",G45<>"",I45<>""), (G45-F45)/(F45-I45), "") | M45: =IF(N45>0,"Win",IF(N45<0,"Loss","")) | N45: =IF(AND(F45<>"",G45<>"",H45<>"",D45<>""), IF(E45="Long", (G45-F45)*H45*VLOOKUP(D45,Multipliers!A:B,2,FALSE), (F45-G45)*H45*VLOOKUP(D45,Multipliers!A:B,2,FALSE)), "") | O45: =IF(AND(N45<>"",F45<>"",H45<>"",D45<>""), N45/(F45*H45*VLOOKUP(D45,Multipliers!A:B,2,FALSE)), "") | P45: =P44+N45 | Q45: Break and Retest | R45: Imported from Tradovate | S45: MGC
A46: 51 | B46: 46254 | C46: 0.42015046 | D46: MNQ | E46: Long | F46: 29329.5 | G46: 29323.25 | H46: 2 | I46: 29323.5 | J46: 29383.5 | K46: =IF(AND(I46<>"",J46<>"",F46<>""), (J46-F46)/(F46-I46), "") | L46: =IF(AND(F46<>"",G46<>"",I46<>""), (G46-F46)/(F46-I46), "") | M46: =IF(N46>0,"Win",IF(N46<0,"Loss","")) | N46: =IF(AND(F46<>"",G46<>"",H46<>"",D46<>""), IF(E46="Long", (G46-F46)*H46*VLOOKUP(D46,Multipliers!A:B,2,FALSE), (F46-G46)*H46*VLOOKUP(D46,Multipliers!A:B,2,FALSE)), "") | O46: =IF(AND(N46<>"",F46<>"",H46<>"",D46<>""), N46/(F46*H46*VLOOKUP(D46,Multipliers!A:B,2,FALSE)), "") | P46: =P45+N46 | Q46: Break and Retest | R46: Imported from Tradovate | S46: MNQ
A47: 52 | B47: 46255 | C47: 0.41141204 | D47: MGC | E47: Long | F47: 4638.6 | G47: 4656.6667 | H47: 3 | I47: 4632 | J47: 4660 | K47: =IF(AND(I47<>"",J47<>"",F47<>""), (J47-F47)/(F47-I47), "") | L47: =IF(AND(F47<>"",G47<>"",I47<>""), (G47-F47)/(F47-I47), "") | M47: =IF(N47>0,"Win",IF(N47<0,"Loss","")) | N47: =IF(AND(F47<>"",G47<>"",H47<>"",D47<>""), IF(E47="Long", (G47-F47)*H47*VLOOKUP(D47,Multipliers!A:B,2,FALSE), (F47-G47)*H47*VLOOKUP(D47,Multipliers!A:B,2,FALSE)), "") | O47: =IF(AND(N47<>"",F47<>"",H47<>"",D47<>""), N47/(F47*H47*VLOOKUP(D47,Multipliers!A:B,2,FALSE)), "") | P47: =P46+N47 | Q47: Break and Retest | R47: Imported from Tradovate | S47: MGC
A48: 53 | B48: 46257 | C48: 0.81630787 | D48: MGC | E48: Long | F48: 4640.8 | G48: 4634.6 | H48: 1 | I48: 4634.8 | J48: 4652.8 | K48: =IF(AND(I48<>"",J48<>"",F48<>""), (J48-F48)/(F48-I48), "") | L48: =IF(AND(F48<>"",G48<>"",I48<>""), (G48-F48)/(F48-I48), "") | M48: =IF(N48>0,"Win",IF(N48<0,"Loss","")) | N48: =IF(AND(F48<>"",G48<>"",H48<>"",D48<>""), IF(E48="Long", (G48-F48)*H48*VLOOKUP(D48,Multipliers!A:B,2,FALSE), (F48-G48)*H48*VLOOKUP(D48,Multipliers!A:B,2,FALSE)), "") | O48: =IF(AND(N48<>"",F48<>"",H48<>"",D48<>""), N48/(F48*H48*VLOOKUP(D48,Multipliers!A:B,2,FALSE)), "") | P48: =P47+N48 | Q48: Break and Retest | R48: Imported from Tradovate | S48: MGC
A49: 54 | B49: 46257 | C49: 0.82392361 | D49: MGC | E49: Long | F49: 4631.1 | G49: 4643.1 | H49: 1 | I49: 4625.1 | J49: 4643.1 | K49: =IF(AND(I49<>"",J49<>"",F49<>""), (J49-F49)/(F49-I49), "") | L49: =IF(AND(F49<>"",G49<>"",I49<>""), (G49-F49)/(F49-I49), "") | M49: =IF(N49>0,"Win",IF(N49<0,"Loss","")) | N49: =IF(AND(F49<>"",G49<>"",H49<>"",D49<>""), IF(E49="Long", (G49-F49)*H49*VLOOKUP(D49,Multipliers!A:B,2,FALSE), (F49-G49)*H49*VLOOKUP(D49,Multipliers!A:B,2,FALSE)), "") | O49: =IF(AND(N49<>"",F49<>"",H49<>"",D49<>""), N49/(F49*H49*VLOOKUP(D49,Multipliers!A:B,2,FALSE)), "") | P49: =P48+N49 | Q49: Break and Retest | R49: Imported from Tradovate | S49: MGC | V49: Revenge trade
A50: 55 | B50: 46257 | C50: 0.84993056 | D50: MGC | E50: Long | F50: 4642.3 | G50: 4636.2 | H50: 1 | I50: 4636.3 | J50: 4654.3 | K50: =IF(AND(I50<>"",J50<>"",F50<>""), (J50-F50)/(F50-I50), "") | L50: =IF(AND(F50<>"",G50<>"",I50<>""), (G50-F50)/(F50-I50), "") | M50: =IF(N50>0,"Win",IF(N50<0,"Loss","")) | N50: =IF(AND(F50<>"",G50<>"",H50<>"",D50<>""), IF(E50="Long", (G50-F50)*H50*VLOOKUP(D50,Multipliers!A:B,2,FALSE), (F50-G50)*H50*VLOOKUP(D50,Multipliers!A:B,2,FALSE)), "") | O50: =IF(AND(N50<>"",F50<>"",H50<>"",D50<>""), N50/(F50*H50*VLOOKUP(D50,Multipliers!A:B,2,FALSE)), "") | P50: =P49+N50 | Q50: Break and Retest | R50: Imported from Tradovate | S50: MGC
A51: 56 | B51: 46257 | C51: 0.85321759 | D51: MGC | E51: Long | F51: 4630.1 | G51: 4641.55 | H51: 2 | I51: 4620.8 | J51: 4643.1 | K51: =IF(AND(I51<>"",J51<>"",F51<>""), (J51-F51)/(F51-I51), "") | L51: =IF(AND(F51<>"",G51<>"",I51<>""), (G51-F51)/(F51-I51), "") | M51: =IF(N51>0,"Win",IF(N51<0,"Loss","")) | N51: =IF(AND(F51<>"",G51<>"",H51<>"",D51<>""), IF(E51="Long", (G51-F51)*H51*VLOOKUP(D51,Multipliers!A:B,2,FALSE), (F51-G51)*H51*VLOOKUP(D51,Multipliers!A:B,2,FALSE)), "") | O51: =IF(AND(N51<>"",F51<>"",H51<>"",D51<>""), N51/(F51*H51*VLOOKUP(D51,Multipliers!A:B,2,FALSE)), "") | P51: =P50+N51 | Q51: Break and Retest | R51: Imported from Tradovate | S51: MGC | V51: Revenge trade
A52: 57 | B52: 46257 | C52: 0.95665509 | D52: MGC | E52: Long | F52: 4663.7 | G52: 4657.4 | H52: 1 | I52: 4657.7 | J52: 4675.7 | K52: =IF(AND(I52<>"",J52<>"",F52<>""), (J52-F52)/(F52-I52), "") | L52: =IF(AND(F52<>"",G52<>"",I52<>""), (G52-F52)/(F52-I52), "") | M52: =IF(N52>0,"Win",IF(N52<0,"Loss","")) | N52: =IF(AND(F52<>"",G52<>"",H52<>"",D52<>""), IF(E52="Long", (G52-F52)*H52*VLOOKUP(D52,Multipliers!A:B,2,FALSE), (F52-G52)*H52*VLOOKUP(D52,Multipliers!A:B,2,FALSE)), "") | O52: =IF(AND(N52<>"",F52<>"",H52<>"",D52<>""), N52/(F52*H52*VLOOKUP(D52,Multipliers!A:B,2,FALSE)), "") | P52: =P51+N52 | Q52: Break and Retest | R52: Imported from Tradovate | S52: MGC
A53: 58 | B53: 46258 | C53: 0.012731481 | D53: MGC | E53: Long | F53: 4695.3333 | G53: 4695.8667 | H53: 3 | I53: 4688.5 | J53: 4696.2 | K53: =IF(AND(I53<>"",J53<>"",F53<>""), (J53-F53)/(F53-I53), "") | L53: =IF(AND(F53<>"",G53<>"",I53<>""), (G53-F53)/(F53-I53), "") | M53: =IF(N53>0,"Win",IF(N53<0,"Loss","")) | N53: =IF(AND(F53<>"",G53<>"",H53<>"",D53<>""), IF(E53="Long", (G53-F53)*H53*VLOOKUP(D53,Multipliers!A:B,2,FALSE), (F53-G53)*H53*VLOOKUP(D53,Multipliers!A:B,2,FALSE)), "") | O53: =IF(AND(N53<>"",F53<>"",H53<>"",D53<>""), N53/(F53*H53*VLOOKUP(D53,Multipliers!A:B,2,FALSE)), "") | P53: =P52+N53 | Q53: Break and Retest | R53: Imported from Tradovate | S53: MGC
A54: 59 | B54: 46258 | C54: 0.40234954 | D54: MGC | E54: Long | F54: 4725.3 | G54: 4719.3 | H54: 2 | I54: 4719.3 | J54: 4742.7 | K54: =IF(AND(I54<>"",J54<>"",F54<>""), (J54-F54)/(F54-I54), "") | L54: =IF(AND(F54<>"",G54<>"",I54<>""), (G54-F54)/(F54-I54), "") | M54: =IF(N54>0,"Win",IF(N54<0,"Loss","")) | N54: =IF(AND(F54<>"",G54<>"",H54<>"",D54<>""), IF(E54="Long", (G54-F54)*H54*VLOOKUP(D54,Multipliers!A:B,2,FALSE), (F54-G54)*H54*VLOOKUP(D54,Multipliers!A:B,2,FALSE)), "") | O54: =IF(AND(N54<>"",F54<>"",H54<>"",D54<>""), N54/(F54*H54*VLOOKUP(D54,Multipliers!A:B,2,FALSE)), "") | P54: =P53+N54 | Q54: Break and Retest | R54: Imported from Tradovate | S54: MGC | V54: Revenge trade | W54: FOMO, Ranging, Outside session
A55: 60 | B55: 46258 | C55: 0.45706019 | D55: MNQ | E55: Long | F55: 29081.5 | G55: 29063.75 | H55: 3 | I55: 29063.75 | J55: 29085.25 | K55: =IF(AND(I55<>"",J55<>"",F55<>""), (J55-F55)/(F55-I55), "") | L55: =IF(AND(F55<>"",G55<>"",I55<>""), (G55-F55)/(F55-I55), "") | M55: =IF(N55>0,"Win",IF(N55<0,"Loss","")) | N55: =IF(AND(F55<>"",G55<>"",H55<>"",D55<>""), IF(E55="Long", (G55-F55)*H55*VLOOKUP(D55,Multipliers!A:B,2,FALSE), (F55-G55)*H55*VLOOKUP(D55,Multipliers!A:B,2,FALSE)), "") | O55: =IF(AND(N55<>"",F55<>"",H55<>"",D55<>""), N55/(F55*H55*VLOOKUP(D55,Multipliers!A:B,2,FALSE)), "") | P55: =P54+N55 | Q55: Break and Retest | R55: Imported from Tradovate | S55: MNQ
A56: 61 | B56: 46258 | C56: 0.46740741 | D56: MNQ | E56: Short | F56: 29068.75 | G56: 29092.75 | H56: 5 | I56: 29101.5 | J56: 29044.25 | K56: =IF(AND(I56<>"",J56<>"",F56<>""), (J56-F56)/(F56-I56), "") | L56: =IF(AND(F56<>"",G56<>"",I56<>""), (G56-F56)/(F56-I56), "") | M56: =IF(N56>0,"Win",IF(N56<0,"Loss","")) | N56: =IF(AND(F56<>"",G56<>"",H56<>"",D56<>""), IF(E56="Long", (G56-F56)*H56*VLOOKUP(D56,Multipliers!A:B,2,FALSE), (F56-G56)*H56*VLOOKUP(D56,Multipliers!A:B,2,FALSE)), "") | O56: =IF(AND(N56<>"",F56<>"",H56<>"",D56<>""), N56/(F56*H56*VLOOKUP(D56,Multipliers!A:B,2,FALSE)), "") | P56: =P55+N56 | Q56: Break and Retest | R56: Imported from Tradovate | S56: MNQ | V56: Revenge trade | X56: Trending up
A57: 62 | B57: 46259 | C57: 0.41013889 | D57: MGC | E57: Short | F57: 4664 | G57: 4671.5 | H57: 3 | I57: 4671.3 | J57: 4652 | K57: =IF(AND(I57<>"",J57<>"",F57<>""), (J57-F57)/(F57-I57), "") | L57: =IF(AND(F57<>"",G57<>"",I57<>""), (G57-F57)/(F57-I57), "") | M57: =IF(N57>0,"Win",IF(N57<0,"Loss","")) | N57: =IF(AND(F57<>"",G57<>"",H57<>"",D57<>""), IF(E57="Long", (G57-F57)*H57*VLOOKUP(D57,Multipliers!A:B,2,FALSE), (F57-G57)*H57*VLOOKUP(D57,Multipliers!A:B,2,FALSE)), "") | O57: =IF(AND(N57<>"",F57<>"",H57<>"",D57<>""), N57/(F57*H57*VLOOKUP(D57,Multipliers!A:B,2,FALSE)), "") | P57: =P56+N57 | Q57: Break and Retest, Rejection | R57: Imported from Tradovate | S57: MGC
A58: 63 | B58: 46259 | C58: 0.43224537 | D58: MNQ | E58: Long | F58: 29238.75 | G58: 29229.75 | H58: 5 | I58: 29226.25 | J58: 29286.25 | K58: =IF(AND(I58<>"",J58<>"",F58<>""), (J58-F58)/(F58-I58), "") | L58: =IF(AND(F58<>"",G58<>"",I58<>""), (G58-F58)/(F58-I58), "") | M58: =IF(N58>0,"Win",IF(N58<0,"Loss","")) | N58: =IF(AND(F58<>"",G58<>"",H58<>"",D58<>""), IF(E58="Long", (G58-F58)*H58*VLOOKUP(D58,Multipliers!A:B,2,FALSE), (F58-G58)*H58*VLOOKUP(D58,Multipliers!A:B,2,FALSE)), "") | O58: =IF(AND(N58<>"",F58<>"",H58<>"",D58<>""), N58/(F58*H58*VLOOKUP(D58,Multipliers!A:B,2,FALSE)), "") | P58: =P57+N58 | Q58: Break and Retest | R58: Imported from Tradovate | S58: MNQ
A59: 64 | B59: 46259 | C59: 0.4391088 | D59: MNQ | E59: Short | F59: 29245.5 | G59: 29229.417 | H59: 3 | I59: 29278 | J59: 29175.25 | K59: =IF(AND(I59<>"",J59<>"",F59<>""), (J59-F59)/(F59-I59), "") | L59: =IF(AND(F59<>"",G59<>"",I59<>""), (G59-F59)/(F59-I59), "") | M59: =IF(N59>0,"Win",IF(N59<0,"Loss","")) | N59: =IF(AND(F59<>"",G59<>"",H59<>"",D59<>""), IF(E59="Long", (G59-F59)*H59*VLOOKUP(D59,Multipliers!A:B,2,FALSE), (F59-G59)*H59*VLOOKUP(D59,Multipliers!A:B,2,FALSE)), "") | O59: =IF(AND(N59<>"",F59<>"",H59<>"",D59<>""), N59/(F59*H59*VLOOKUP(D59,Multipliers!A:B,2,FALSE)), "") | P59: =P58+N59 | Q59: Break and Retest | R59: Imported from Tradovate | S59: MNQ | V59: Cut winner early
A60: 65 | B60: 46259 | C60: 0.5224537 | D60: MGC | E60: Short | F60: 4699.4 | G60: 4699.1 | H60: 3 | I60: 4705.8 | J60: 4699.1 | K60: =IF(AND(I60<>"",J60<>"",F60<>""), (J60-F60)/(F60-I60), "") | L60: =IF(AND(F60<>"",G60<>"",I60<>""), (G60-F60)/(F60-I60), "") | M60: =IF(N60>0,"Win",IF(N60<0,"Loss","")) | N60: =IF(AND(F60<>"",G60<>"",H60<>"",D60<>""), IF(E60="Long", (G60-F60)*H60*VLOOKUP(D60,Multipliers!A:B,2,FALSE), (F60-G60)*H60*VLOOKUP(D60,Multipliers!A:B,2,FALSE)), "") | O60: =IF(AND(N60<>"",F60<>"",H60<>"",D60<>""), N60/(F60*H60*VLOOKUP(D60,Multipliers!A:B,2,FALSE)), "") | P60: =P59+N60 | Q60: Break and Retest | R60: Imported from Tradovate | S60: MGC
A61: 66 | B61: 46259 | C61: 0.97207176 | D61: MGC | E61: Short | F61: 4703.7 | G61: 4703 | H61: 5 | J61: 4703 | K61: =IF(AND(I61<>"",J61<>"",F61<>""), (J61-F61)/(F61-I61), "") | L61: =IF(AND(F61<>"",G61<>"",I61<>""), (G61-F61)/(F61-I61), "") | M61: =IF(N61>0,"Win",IF(N61<0,"Loss","")) | N61: =IF(AND(F61<>"",G61<>"",H61<>"",D61<>""), IF(E61="Long", (G61-F61)*H61*VLOOKUP(D61,Multipliers!A:B,2,FALSE), (F61-G61)*H61*VLOOKUP(D61,Multipliers!A:B,2,FALSE)), "") | O61: =IF(AND(N61<>"",F61<>"",H61<>"",D61<>""), N61/(F61*H61*VLOOKUP(D61,Multipliers!A:B,2,FALSE)), "") | P61: =P60+N61 | Q61: Break and Retest | R61: Imported from Tradovate | S61: MGC
A62: 67 | B62: 46260 | C62: 0.4103125 | D62: MGC | E62: Long | F62: 4679.6 | G62: 4680.3 | H62: 3 | I62: 4673.7 | J62: 4680.3 | K62: =IF(AND(I62<>"",J62<>"",F62<>""), (J62-F62)/(F62-I62), "") | L62: =IF(AND(F62<>"",G62<>"",I62<>""), (G62-F62)/(F62-I62), "") | M62: =IF(N62>0,"Win",IF(N62<0,"Loss","")) | N62: =IF(AND(F62<>"",G62<>"",H62<>"",D62<>""), IF(E62="Long", (G62-F62)*H62*VLOOKUP(D62,Multipliers!A:B,2,FALSE), (F62-G62)*H62*VLOOKUP(D62,Multipliers!A:B,2,FALSE)), "") | O62: =IF(AND(N62<>"",F62<>"",H62<>"",D62<>""), N62/(F62*H62*VLOOKUP(D62,Multipliers!A:B,2,FALSE)), "") | P62: =P61+N62 | Q62: Break and Retest | R62: Imported from Tradovate | S62: MGC | V62: Overtraded
A63: 68 | B63: 46260 | C63: 0.42958333 | D63: MGC | E63: Short | F63: 4679.5 | G63: 4676.3 | H63: 3 | I63: 4685.5 | J63: 4676.3 | K63: =IF(AND(I63<>"",J63<>"",F63<>""), (J63-F63)/(F63-I63), "") | L63: =IF(AND(F63<>"",G63<>"",I63<>""), (G63-F63)/(F63-I63), "") | M63: =IF(N63>0,"Win",IF(N63<0,"Loss","")) | N63: =IF(AND(F63<>"",G63<>"",H63<>"",D63<>""), IF(E63="Long", (G63-F63)*H63*VLOOKUP(D63,Multipliers!A:B,2,FALSE), (F63-G63)*H63*VLOOKUP(D63,Multipliers!A:B,2,FALSE)), "") | O63: =IF(AND(N63<>"",F63<>"",H63<>"",D63<>""), N63/(F63*H63*VLOOKUP(D63,Multipliers!A:B,2,FALSE)), "") | P63: =P62+N63 | Q63: Break and Retest | R63: Imported from Tradovate | S63: MGC | V63: Overtraded
A64: 69 | B64: 46260 | C64: 0.49040509 | D64: MGC | E64: Long | F64: 4661.7 | G64: 4656.2 | H64: 3 | I64: 4656.2 | J64: 4674.2 | K64: =IF(AND(I64<>"",J64<>"",F64<>""), (J64-F64)/(F64-I64), "") | L64: =IF(AND(F64<>"",G64<>"",I64<>""), (G64-F64)/(F64-I64), "") | M64: =IF(N64>0,"Win",IF(N64<0,"Loss","")) | N64: =IF(AND(F64<>"",G64<>"",H64<>"",D64<>""), IF(E64="Long", (G64-F64)*H64*VLOOKUP(D64,Multipliers!A:B,2,FALSE), (F64-G64)*H64*VLOOKUP(D64,Multipliers!A:B,2,FALSE)), "") | O64: =IF(AND(N64<>"",F64<>"",H64<>"",D64<>""), N64/(F64*H64*VLOOKUP(D64,Multipliers!A:B,2,FALSE)), "") | P64: =P63+N64 | Q64: Break and Retest | R64: Imported from Tradovate | S64: MGC | V64: Overtraded
A65: 70 | B65: 46260 | C65: 0.49684028 | D65: MGC | E65: Short | F65: 4655.8 | G65: 4652.1 | H65: 5 | J65: 4652.1 | K65: =IF(AND(I65<>"",J65<>"",F65<>""), (J65-F65)/(F65-I65), "") | L65: =IF(AND(F65<>"",G65<>"",I65<>""), (G65-F65)/(F65-I65), "") | M65: =IF(N65>0,"Win",IF(N65<0,"Loss","")) | N65: =IF(AND(F65<>"",G65<>"",H65<>"",D65<>""), IF(E65="Long", (G65-F65)*H65*VLOOKUP(D65,Multipliers!A:B,2,FALSE), (F65-G65)*H65*VLOOKUP(D65,Multipliers!A:B,2,FALSE)), "") | O65: =IF(AND(N65<>"",F65<>"",H65<>"",D65<>""), N65/(F65*H65*VLOOKUP(D65,Multipliers!A:B,2,FALSE)), "") | P65: =P64+N65 | Q65: Break and Retest | R65: Imported from Tradovate | S65: MGC | V65: Revenge trade, Overtraded
A66: 71 | B66: 46260 | C66: 0.54947917 | D66: MGC | E66: Short | F66: 4649.2 | G66: 4657.7 | H66: 3 | I66: 4661 | J66: 4649.1 | K66: =IF(AND(I66<>"",J66<>"",F66<>""), (J66-F66)/(F66-I66), "") | L66: =IF(AND(F66<>"",G66<>"",I66<>""), (G66-F66)/(F66-I66), "") | M66: =IF(N66>0,"Win",IF(N66<0,"Loss","")) | N66: =IF(AND(F66<>"",G66<>"",H66<>"",D66<>""), IF(E66="Long", (G66-F66)*H66*VLOOKUP(D66,Multipliers!A:B,2,FALSE), (F66-G66)*H66*VLOOKUP(D66,Multipliers!A:B,2,FALSE)), "") | O66: =IF(AND(N66<>"",F66<>"",H66<>"",D66<>""), N66/(F66*H66*VLOOKUP(D66,Multipliers!A:B,2,FALSE)), "") | P66: =P65+N66 | Q66: Break and Retest | R66: Imported from Tradovate | S66: MGC | V66: Overtraded
A67: 72 | B67: 46260 | C67: 0.8296875 | D67: MNQ | E67: Long | F67: 29614.5 | G67: 29655.25 | H67: 1 | I67: 29595.25 | J67: 29655.25 | K67: =IF(AND(I67<>"",J67<>"",F67<>""), (J67-F67)/(F67-I67), "") | L67: =IF(AND(F67<>"",G67<>"",I67<>""), (G67-F67)/(F67-I67), "") | M67: =IF(N67>0,"Win",IF(N67<0,"Loss","")) | N67: =IF(AND(F67<>"",G67<>"",H67<>"",D67<>""), IF(E67="Long", (G67-F67)*H67*VLOOKUP(D67,Multipliers!A:B,2,FALSE), (F67-G67)*H67*VLOOKUP(D67,Multipliers!A:B,2,FALSE)), "") | O67: =IF(AND(N67<>"",F67<>"",H67<>"",D67<>""), N67/(F67*H67*VLOOKUP(D67,Multipliers!A:B,2,FALSE)), "") | P67: =P66+N67 | Q67: Break and Retest | R67: Imported from Tradovate | S67: MNQ | V67: Overtraded
A68: 73 | B68: 46260 | C68: 0.83674769 | D68: MNQ | E68: Long | F68: 29613.5 | G68: 29593.25 | H68: 2 | I68: 29593.5 | J68: 29653.5 | K68: =IF(AND(I68<>"",J68<>"",F68<>""), (J68-F68)/(F68-I68), "") | L68: =IF(AND(F68<>"",G68<>"",I68<>""), (G68-F68)/(F68-I68), "") | M68: =IF(N68>0,"Win",IF(N68<0,"Loss","")) | N68: =IF(AND(F68<>"",G68<>"",H68<>"",D68<>""), IF(E68="Long", (G68-F68)*H68*VLOOKUP(D68,Multipliers!A:B,2,FALSE), (F68-G68)*H68*VLOOKUP(D68,Multipliers!A:B,2,FALSE)), "") | O68: =IF(AND(N68<>"",F68<>"",H68<>"",D68<>""), N68/(F68*H68*VLOOKUP(D68,Multipliers!A:B,2,FALSE)), "") | P68: =P67+N68 | Q68: Break and Retest | R68: Imported from Tradovate | S68: MNQ | V68: Overtraded
A69: 74 | B69: 46260 | C69: 0.87857639 | D69: MNQ | E69: Long | F69: 29467.25 | G69: 29447.25 | H69: 3 | I69: 29429.75 | J69: 29509.75 | K69: =IF(AND(I69<>"",J69<>"",F69<>""), (J69-F69)/(F69-I69), "") | L69: =IF(AND(F69<>"",G69<>"",I69<>""), (G69-F69)/(F69-I69), "") | M69: =IF(N69>0,"Win",IF(N69<0,"Loss","")) | N69: =IF(AND(F69<>"",G69<>"",H69<>"",D69<>""), IF(E69="Long", (G69-F69)*H69*VLOOKUP(D69,Multipliers!A:B,2,FALSE), (F69-G69)*H69*VLOOKUP(D69,Multipliers!A:B,2,FALSE)), "") | O69: =IF(AND(N69<>"",F69<>"",H69<>"",D69<>""), N69/(F69*H69*VLOOKUP(D69,Multipliers!A:B,2,FALSE)), "") | P69: =P68+N69 | Q69: Break and Retest | R69: Imported from Tradovate | S69: MNQ | V69: Overtraded
A70: 75 | B70: 46260 | C70: 0.88644676 | D70: MNQ | E70: Long | F70: 29484.354 | G70: 29496.958 | H70: 12 | I70: 29429.75 | J70: 29508 | K70: =IF(AND(I70<>"",J70<>"",F70<>""), (J70-F70)/(F70-I70), "") | L70: =IF(AND(F70<>"",G70<>"",I70<>""), (G70-F70)/(F70-I70), "") | M70: =IF(N70>0,"Win",IF(N70<0,"Loss","")) | N70: =IF(AND(F70<>"",G70<>"",H70<>"",D70<>""), IF(E70="Long", (G70-F70)*H70*VLOOKUP(D70,Multipliers!A:B,2,FALSE), (F70-G70)*H70*VLOOKUP(D70,Multipliers!A:B,2,FALSE)), "") | O70: =IF(AND(N70<>"",F70<>"",H70<>"",D70<>""), N70/(F70*H70*VLOOKUP(D70,Multipliers!A:B,2,FALSE)), "") | P70: =P69+N70 | Q70: Break and Retest | R70: Imported from Tradovate | S70: MNQ | V70: Oversized, Revenge trade, Overtraded
A71: 76 | B71: 46260 | C71: 0.89381944 | D71: MNQ | E71: Long | F71: 29504.25 | G71: 29514.75 | H71: 2 | J71: 29514.75 | K71: =IF(AND(I71<>"",J71<>"",F71<>""), (J71-F71)/(F71-I71), "") | L71: =IF(AND(F71<>"",G71<>"",I71<>""), (G71-F71)/(F71-I71), "") | M71: =IF(N71>0,"Win",IF(N71<0,"Loss","")) | N71: =IF(AND(F71<>"",G71<>"",H71<>"",D71<>""), IF(E71="Long", (G71-F71)*H71*VLOOKUP(D71,Multipliers!A:B,2,FALSE), (F71-G71)*H71*VLOOKUP(D71,Multipliers!A:B,2,FALSE)), "") | O71: =IF(AND(N71<>"",F71<>"",H71<>"",D71<>""), N71/(F71*H71*VLOOKUP(D71,Multipliers!A:B,2,FALSE)), "") | P71: =P70+N71 | Q71: Break and Retest | R71: Imported from Tradovate | S71: MNQ | V71: Overtraded
A72: 77 | B72: 46260 | C72: 0.89982639 | D72: MNQ | E72: Long | F72: 29515.5 | G72: 29530.25 | H72: 3 | J72: 29530.25 | K72: =IF(AND(I72<>"",J72<>"",F72<>""), (J72-F72)/(F72-I72), "") | L72: =IF(AND(F72<>"",G72<>"",I72<>""), (G72-F72)/(F72-I72), "") | M72: =IF(N72>0,"Win",IF(N72<0,"Loss","")) | N72: =IF(AND(F72<>"",G72<>"",H72<>"",D72<>""), IF(E72="Long", (G72-F72)*H72*VLOOKUP(D72,Multipliers!A:B,2,FALSE), (F72-G72)*H72*VLOOKUP(D72,Multipliers!A:B,2,FALSE)), "") | O72: =IF(AND(N72<>"",F72<>"",H72<>"",D72<>""), N72/(F72*H72*VLOOKUP(D72,Multipliers!A:B,2,FALSE)), "") | P72: =P71+N72 | Q72: Break and Retest | R72: Imported from Tradovate | S72: MNQ | V72: Overtraded
A73: 78 | B73: 46260 | C73: 0.9321412 | D73: MNQ | E73: Short | F73: 29534 | G73: 29529 | H73: 5 | I73: 29549 | J73: 29529 | K73: =IF(AND(I73<>"",J73<>"",F73<>""), (J73-F73)/(F73-I73), "") | L73: =IF(AND(F73<>"",G73<>"",I73<>""), (G73-F73)/(F73-I73), "") | M73: =IF(N73>0,"Win",IF(N73<0,"Loss","")) | N73: =IF(AND(F73<>"",G73<>"",H73<>"",D73<>""), IF(E73="Long", (G73-F73)*H73*VLOOKUP(D73,Multipliers!A:B,2,FALSE), (F73-G73)*H73*VLOOKUP(D73,Multipliers!A:B,2,FALSE)), "") | O73: =IF(AND(N73<>"",F73<>"",H73<>"",D73<>""), N73/(F73*H73*VLOOKUP(D73,Multipliers!A:B,2,FALSE)), "") | P73: =P72+N73 | Q73: Break and Retest | R73: Imported from Tradovate | S73: MNQ | V73: Overtraded
A74: 79 | B74: 46261 | C74: 0.40553241 | D74: MGC | E74: Short | F74: 4633.6 | G74: 4621.6 | H74: 3 | I74: 4639.6 | J74: 4621.6 | K74: =IF(AND(I74<>"",J74<>"",F74<>""), (J74-F74)/(F74-I74), "") | L74: =IF(AND(F74<>"",G74<>"",I74<>""), (G74-F74)/(F74-I74), "") | M74: =IF(N74>0,"Win",IF(N74<0,"Loss","")) | N74: =IF(AND(F74<>"",G74<>"",H74<>"",D74<>""), IF(E74="Long", (G74-F74)*H74*VLOOKUP(D74,Multipliers!A:B,2,FALSE), (F74-G74)*H74*VLOOKUP(D74,Multipliers!A:B,2,FALSE)), "") | O74: =IF(AND(N74<>"",F74<>"",H74<>"",D74<>""), N74/(F74*H74*VLOOKUP(D74,Multipliers!A:B,2,FALSE)), "") | P74: =P73+N74 | Q74: Break and Retest | R74: Imported from Tradovate | S74: MGC | U74: https://www.tradingview.com/x/ThCH9HRj/ | V74: Overtraded
A75: 80 | B75: 46261 | C75: 0.42893519 | D75: MGC | E75: Short | F75: 4635.2 | G75: 4633.4 | H75: 3 | I75: 4641.2 | J75: 4633.4 | K75: =IF(AND(I75<>"",J75<>"",F75<>""), (J75-F75)/(F75-I75), "") | L75: =IF(AND(F75<>"",G75<>"",I75<>""), (G75-F75)/(F75-I75), "") | M75: =IF(N75>0,"Win",IF(N75<0,"Loss","")) | N75: =IF(AND(F75<>"",G75<>"",H75<>"",D75<>""), IF(E75="Long", (G75-F75)*H75*VLOOKUP(D75,Multipliers!A:B,2,FALSE), (F75-G75)*H75*VLOOKUP(D75,Multipliers!A:B,2,FALSE)), "") | O75: =IF(AND(N75<>"",F75<>"",H75<>"",D75<>""), N75/(F75*H75*VLOOKUP(D75,Multipliers!A:B,2,FALSE)), "") | P75: =P74+N75 | Q75: Break and Retest | R75: Imported from Tradovate | S75: MGC | U75: https://www.tradingview.com/x/ThCH9HRj/
A76: 81 | B76: 46262 | C76: 0.42315972 | D76: MGC | E76: Short | F76: 4629.7 | G76: 4608.4 | H76: 2 | I76: 4635.8 | J76: 4609 | K76: =IF(AND(I76<>"",J76<>"",F76<>""), (J76-F76)/(F76-I76), "") | L76: =IF(AND(F76<>"",G76<>"",I76<>""), (G76-F76)/(F76-I76), "") | M76: =IF(N76>0,"Win",IF(N76<0,"Loss","")) | N76: =IF(AND(F76<>"",G76<>"",H76<>"",D76<>""), IF(E76="Long", (G76-F76)*H76*VLOOKUP(D76,Multipliers!A:B,2,FALSE), (F76-G76)*H76*VLOOKUP(D76,Multipliers!A:B,2,FALSE)), "") | O76: =IF(AND(N76<>"",F76<>"",H76<>"",D76<>""), N76/(F76*H76*VLOOKUP(D76,Multipliers!A:B,2,FALSE)), "") | P76: =P75+N76 | Q76: Break and Retest | R76: Imported from Tradovate | S76: MGC
A77: 82 | B77: 46262 | C77: 0.4344213 | D77: MNQ | E77: Short | F77: 29642.25 | G77: 29608.75 | H77: 2 | I77: 29684 | J77: 29608.25 | K77: =IF(AND(I77<>"",J77<>"",F77<>""), (J77-F77)/(F77-I77), "") | L77: =IF(AND(F77<>"",G77<>"",I77<>""), (G77-F77)/(F77-I77), "") | M77: =IF(N77>0,"Win",IF(N77<0,"Loss","")) | N77: =IF(AND(F77<>"",G77<>"",H77<>"",D77<>""), IF(E77="Long", (G77-F77)*H77*VLOOKUP(D77,Multipliers!A:B,2,FALSE), (F77-G77)*H77*VLOOKUP(D77,Multipliers!A:B,2,FALSE)), "") | O77: =IF(AND(N77<>"",F77<>"",H77<>"",D77<>""), N77/(F77*H77*VLOOKUP(D77,Multipliers!A:B,2,FALSE)), "") | P77: =P76+N77 | Q77: Rejection | R77: Imported from Tradovate | S77: MNQ | V77: Cut winner early
A78: 83 | B78: 46262 | C78: 0.44475694 | D78: MNQ | E78: Short | F78: 29692.25 | G78: 29717.75 | H78: 2 | I78: 29717.5 | J78: 29647 | K78: =IF(AND(I78<>"",J78<>"",F78<>""), (J78-F78)/(F78-I78), "") | L78: =IF(AND(F78<>"",G78<>"",I78<>""), (G78-F78)/(F78-I78), "") | M78: =IF(N78>0,"Win",IF(N78<0,"Loss","")) | N78: =IF(AND(F78<>"",G78<>"",H78<>"",D78<>""), IF(E78="Long", (G78-F78)*H78*VLOOKUP(D78,Multipliers!A:B,2,FALSE), (F78-G78)*H78*VLOOKUP(D78,Multipliers!A:B,2,FALSE)), "") | O78: =IF(AND(N78<>"",F78<>"",H78<>"",D78<>""), N78/(F78*H78*VLOOKUP(D78,Multipliers!A:B,2,FALSE)), "") | P78: =P77+N78 | Q78: Break and Retest | R78: Imported from Tradovate | S78: MNQ
A79: 84 | B79: 46262 | C79: 0.46717593 | D79: MNQ | E79: Short | F79: 29747.5 | G79: 29749.75 | H79: 3 | I79: 29759.75 | K79: =IF(AND(I79<>"",J79<>"",F79<>""), (J79-F79)/(F79-I79), "") | L79: =IF(AND(F79<>"",G79<>"",I79<>""), (G79-F79)/(F79-I79), "") | M79: =IF(N79>0,"Win",IF(N79<0,"Loss","")) | N79: =IF(AND(F79<>"",G79<>"",H79<>"",D79<>""), IF(E79="Long", (G79-F79)*H79*VLOOKUP(D79,Multipliers!A:B,2,FALSE), (F79-G79)*H79*VLOOKUP(D79,Multipliers!A:B,2,FALSE)), "") | O79: =IF(AND(N79<>"",F79<>"",H79<>"",D79<>""), N79/(F79*H79*VLOOKUP(D79,Multipliers!A:B,2,FALSE)), "") | P79: =P78+N79 | Q79: Break and Retest | R79: Imported from Tradovate | S79: MNQ
A80: 85 | B80: 46262 | C80: 0.53708333 | D80: MNQ | E80: Long | F80: 29537.25 | G80: 29510.25 | H80: 3 | I80: 29510.25 | J80: 29557.75 | K80: =IF(AND(I80<>"",J80<>"",F80<>""), (J80-F80)/(F80-I80), "") | L80: =IF(AND(F80<>"",G80<>"",I80<>""), (G80-F80)/(F80-I80), "") | M80: =IF(N80>0,"Win",IF(N80<0,"Loss","")) | N80: =IF(AND(F80<>"",G80<>"",H80<>"",D80<>""), IF(E80="Long", (G80-F80)*H80*VLOOKUP(D80,Multipliers!A:B,2,FALSE), (F80-G80)*H80*VLOOKUP(D80,Multipliers!A:B,2,FALSE)), "") | O80: =IF(AND(N80<>"",F80<>"",H80<>"",D80<>""), N80/(F80*H80*VLOOKUP(D80,Multipliers!A:B,2,FALSE)), "") | P80: =P79+N80 | Q80: Break and Retest | R80: Imported from Tradovate | S80: MNQ
A81: 86 | B81: 46264 | C81: 0.75259259 | D81: MGC | E81: Long | F81: 4499.6 | G81: 4506.2333 | H81: 3 | I81: 4482.5 | J81: 4506.5 | K81: =IF(AND(I81<>"",J81<>"",F81<>""), (J81-F81)/(F81-I81), "") | L81: =IF(AND(F81<>"",G81<>"",I81<>""), (G81-F81)/(F81-I81), "") | M81: =IF(N81>0,"Win",IF(N81<0,"Loss","")) | N81: =IF(AND(F81<>"",G81<>"",H81<>"",D81<>""), IF(E81="Long", (G81-F81)*H81*VLOOKUP(D81,Multipliers!A:B,2,FALSE), (F81-G81)*H81*VLOOKUP(D81,Multipliers!A:B,2,FALSE)), "") | O81: =IF(AND(N81<>"",F81<>"",H81<>"",D81<>""), N81/(F81*H81*VLOOKUP(D81,Multipliers!A:B,2,FALSE)), "") | P81: =P80+N81 | Q81: Gap up | R81: Imported from Tradovate | S81: MGC
A82: 87 | B82: 46264 | C82: 0.76960648 | D82: MGC | E82: Short | F82: 4508.9333 | G82: 4508.1 | H82: 3 | I82: 4521.7 | J82: 4508.2 | K82: =IF(AND(I82<>"",J82<>"",F82<>""), (J82-F82)/(F82-I82), "") | L82: =IF(AND(F82<>"",G82<>"",I82<>""), (G82-F82)/(F82-I82), "") | M82: =IF(N82>0,"Win",IF(N82<0,"Loss","")) | N82: =IF(AND(F82<>"",G82<>"",H82<>"",D82<>""), IF(E82="Long", (G82-F82)*H82*VLOOKUP(D82,Multipliers!A:B,2,FALSE), (F82-G82)*H82*VLOOKUP(D82,Multipliers!A:B,2,FALSE)), "") | O82: =IF(AND(N82<>"",F82<>"",H82<>"",D82<>""), N82/(F82*H82*VLOOKUP(D82,Multipliers!A:B,2,FALSE)), "") | P82: =P81+N82 | Q82: ZTH Indicator | R82: Imported from Tradovate | S82: MGC
A83: 88 | B83: 46265 | C83: 0.0048611111 | D83: MGC | E83: Short | F83: 4468.4 | G83: 4466.8333 | H83: 3 | I83: 4472.6 | J83: 4466.7 | K83: =IF(AND(I83<>"",J83<>"",F83<>""), (J83-F83)/(F83-I83), "") | L83: =IF(AND(F83<>"",G83<>"",I83<>""), (G83-F83)/(F83-I83), "") | M83: =IF(N83>0,"Win",IF(N83<0,"Loss","")) | N83: =IF(AND(F83<>"",G83<>"",H83<>"",D83<>""), IF(E83="Long", (G83-F83)*H83*VLOOKUP(D83,Multipliers!A:B,2,FALSE), (F83-G83)*H83*VLOOKUP(D83,Multipliers!A:B,2,FALSE)), "") | O83: =IF(AND(N83<>"",F83<>"",H83<>"",D83<>""), N83/(F83*H83*VLOOKUP(D83,Multipliers!A:B,2,FALSE)), "") | P83: =P82+N83 | Q83: Break and Retest | R83: Imported from Tradovate | S83: MGC
A84: 89 | B84: 46264 | C84: 0.89261574 | D84: MGC | E84: Short | F84: 4495.4 | G84: 4493.3 | H84: 2 | I84: 4502.9 | J84: 4493.3 | K84: =IF(AND(I84<>"",J84<>"",F84<>""), (J84-F84)/(F84-I84), "") | L84: =IF(AND(F84<>"",G84<>"",I84<>""), (G84-F84)/(F84-I84), "") | M84: =IF(N84>0,"Win",IF(N84<0,"Loss","")) | N84: =IF(AND(F84<>"",G84<>"",H84<>"",D84<>""), IF(E84="Long", (G84-F84)*H84*VLOOKUP(D84,Multipliers!A:B,2,FALSE), (F84-G84)*H84*VLOOKUP(D84,Multipliers!A:B,2,FALSE)), "") | O84: =IF(AND(N84<>"",F84<>"",H84<>"",D84<>""), N84/(F84*H84*VLOOKUP(D84,Multipliers!A:B,2,FALSE)), "") | P84: =P83+N84 | Q84: Break and Retest | R84: Imported from Tradovate | S84: MGC | V84: Oversized
A85: 90 | B85: 46264 | C85: 0.97935185 | D85: MGC | E85: Short | F85: 4472.8333 | G85: 4469.2111 | H85: 9 | I85: 4479.8 | J85: 4466.7 | K85: =IF(AND(I85<>"",J85<>"",F85<>""), (J85-F85)/(F85-I85), "") | L85: =IF(AND(F85<>"",G85<>"",I85<>""), (G85-F85)/(F85-I85), "") | M85: =IF(N85>0,"Win",IF(N85<0,"Loss","")) | N85: =IF(AND(F85<>"",G85<>"",H85<>"",D85<>""), IF(E85="Long", (G85-F85)*H85*VLOOKUP(D85,Multipliers!A:B,2,FALSE), (F85-G85)*H85*VLOOKUP(D85,Multipliers!A:B,2,FALSE)), "") | O85: =IF(AND(N85<>"",F85<>"",H85<>"",D85<>""), N85/(F85*H85*VLOOKUP(D85,Multipliers!A:B,2,FALSE)), "") | P85: =P84+N85 | Q85: ZTH Indicator | R85: Imported from Tradovate | S85: MGC | V85: Oversized
A86: 91 | B86: 46265 | C86: 0.0076736111 | D86: MGC | E86: Long | F86: 4466.7 | G86: 4468.2333 | H86: 3 | J86: 4469 | K86: =IF(AND(I86<>"",J86<>"",F86<>""), (J86-F86)/(F86-I86), "") | L86: =IF(AND(F86<>"",G86<>"",I86<>""), (G86-F86)/(F86-I86), "") | M86: =IF(N86>0,"Win",IF(N86<0,"Loss","")) | N86: =IF(AND(F86<>"",G86<>"",H86<>"",D86<>""), IF(E86="Long", (G86-F86)*H86*VLOOKUP(D86,Multipliers!A:B,2,FALSE), (F86-G86)*H86*VLOOKUP(D86,Multipliers!A:B,2,FALSE)), "") | O86: =IF(AND(N86<>"",F86<>"",H86<>"",D86<>""), N86/(F86*H86*VLOOKUP(D86,Multipliers!A:B,2,FALSE)), "") | P86: =P85+N86 | Q86: Break and Retest | R86: Imported from Tradovate | S86: MGC | V86: Overtraded
A87: 93 | B87: 46265 | C87: 0.4046875 | D87: MNQ | E87: Short | F87: 29429 | G87: 29395.5 | H87: 2 | I87: 29454 | J87: 29395.5 | K87: =IF(AND(I88<>"",J88<>"",F88<>""), (J88-F88)/(F88-I88), "") | L87: =IF(AND(F88<>"",G88<>"",I88<>""), (G88-F88)/(F88-I88), "") | M87: =IF(N88>0,"Win",IF(N88<0,"Loss","")) | N87: =IF(AND(F88<>"",G88<>"",H88<>"",D88<>""), IF(E88="Long", (G88-F88)*H88*VLOOKUP(D88,Multipliers!A:B,2,FALSE), (F88-G88)*H88*VLOOKUP(D88,Multipliers!A:B,2,FALSE)), "") | O87: =IF(AND(N88<>"",F88<>"",H88<>"",D88<>""), N88/(F88*H88*VLOOKUP(D88,Multipliers!A:B,2,FALSE)), "") | P87: =P86+N87 | Q87: Break and Retest | R87: Imported from Tradovate | S87: MNQ | V87: Overtraded
A88: 94 | B88: 46265 | C88: 0.41418981 | D88: MNQ | E88: Long | F88: 29460.75 | G88: 29439.25 | H88: 3 | I88: 29439.25 | J88: 29468 | K88: =IF(AND(I89<>"",J89<>"",F89<>""), (J89-F89)/(F89-I89), "") | L88: =IF(AND(F89<>"",G89<>"",I89<>""), (G89-F89)/(F89-I89), "") | M88: =IF(N89>0,"Win",IF(N89<0,"Loss","")) | N88: =IF(AND(F89<>"",G89<>"",H89<>"",D89<>""), IF(E89="Long", (G89-F89)*H89*VLOOKUP(D89,Multipliers!A:B,2,FALSE), (F89-G89)*H89*VLOOKUP(D89,Multipliers!A:B,2,FALSE)), "") | O88: =IF(AND(N89<>"",F89<>"",H89<>"",D89<>""), N89/(F89*H89*VLOOKUP(D89,Multipliers!A:B,2,FALSE)), "") | P88: =P87+N88 | Q88: Break and Retest | R88: Imported from Tradovate | S88: MNQ | V88: Overtraded
A89: 96 | B89: 46265 | C89: 0.42480324 | D89: MNQ | E89: Short | F89: 29395 | G89: 29415 | H89: 3 | I89: 29415 | J89: 29394 | K89: =IF(AND(I91<>"",J91<>"",F91<>""), (J91-F91)/(F91-I91), "") | L89: =IF(AND(F91<>"",G91<>"",I91<>""), (G91-F91)/(F91-I91), "") | M89: =IF(N91>0,"Win",IF(N91<0,"Loss","")) | N89: =IF(AND(F91<>"",G91<>"",H91<>"",D91<>""), IF(E91="Long", (G91-F91)*H91*VLOOKUP(D91,Multipliers!A:B,2,FALSE), (F91-G91)*H91*VLOOKUP(D91,Multipliers!A:B,2,FALSE)), "") | O89: =IF(AND(N91<>"",F91<>"",H91<>"",D91<>""), N91/(F91*H91*VLOOKUP(D91,Multipliers!A:B,2,FALSE)), "") | P89: =P88+N89 | Q89: Break and Retest | R89: Imported from Tradovate | S89: MNQ | V89: Revenge trade, Overtraded
A90: 97 | B90: 46265 | C90: 0.44520833 | D90: MNQ | E90: Long | F90: 29410 | G90: 29435 | H90: 5 | I90: 29400 | J90: 29435 | K90: =IF(AND(I92<>"",J92<>"",F92<>""), (J92-F92)/(F92-I92), "") | L90: =IF(AND(F92<>"",G92<>"",I92<>""), (G92-F92)/(F92-I92), "") | M90: =IF(N92>0,"Win",IF(N92<0,"Loss","")) | N90: =IF(AND(F92<>"",G92<>"",H92<>"",D92<>""), IF(E92="Long", (G92-F92)*H92*VLOOKUP(D92,Multipliers!A:B,2,FALSE), (F92-G92)*H92*VLOOKUP(D92,Multipliers!A:B,2,FALSE)), "") | O90: =IF(AND(N92<>"",F92<>"",H92<>"",D92<>""), N92/(F92*H92*VLOOKUP(D92,Multipliers!A:B,2,FALSE)), "") | P90: =P89+N90 | Q90: Break and Retest | R90: Imported from Tradovate | S90: MNQ | V90: Overtraded
A91: 98 | B91: 46265 | C91: 0.44966435 | D91: MNQ | E91: Long | F91: 29408.5 | G91: 29399.75 | H91: 5 | I91: 29392.75 | J91: 29443.25 | K91: =IF(AND(I93<>"",J93<>"",F93<>""), (J93-F93)/(F93-I93), "") | L91: =IF(AND(F93<>"",G93<>"",I93<>""), (G93-F93)/(F93-I93), "") | M91: =IF(N93>0,"Win",IF(N93<0,"Loss","")) | N91: =IF(AND(F93<>"",G93<>"",H93<>"",D93<>""), IF(E93="Long", (G93-F93)*H93*VLOOKUP(D93,Multipliers!A:B,2,FALSE), (F93-G93)*H93*VLOOKUP(D93,Multipliers!A:B,2,FALSE)), "") | O91: =IF(AND(N93<>"",F93<>"",H93<>"",D93<>""), N93/(F93*H93*VLOOKUP(D93,Multipliers!A:B,2,FALSE)), "") | P91: =P90+N91 | Q91: Break and Retest | R91: Imported from Tradovate | S91: MNQ | V91: Overtraded
A92: 99 | B92: 46265 | C92: 0.45053241 | D92: MNQ | E92: Long | F92: 29401.5 | G92: 29392 | H92: 3 | I92: 29392.75 | J92: 29443.25 | K92: =IF(AND(I94<>"",J94<>"",F94<>""), (J94-F94)/(F94-I94), "") | L92: =IF(AND(F94<>"",G94<>"",I94<>""), (G94-F94)/(F94-I94), "") | M92: =IF(N94>0,"Win",IF(N94<0,"Loss","")) | N92: =IF(AND(F94<>"",G94<>"",H94<>"",D94<>""), IF(E94="Long", (G94-F94)*H94*VLOOKUP(D94,Multipliers!A:B,2,FALSE), (F94-G94)*H94*VLOOKUP(D94,Multipliers!A:B,2,FALSE)), "") | O92: =IF(AND(N94<>"",F94<>"",H94<>"",D94<>""), N94/(F94*H94*VLOOKUP(D94,Multipliers!A:B,2,FALSE)), "") | P92: =P91+N92 | Q92: Break and Retest | R92: Imported from Tradovate | S92: MNQ | V92: Overtraded
A93: 100 | B93: 46265 | C93: 0.41743056 | D93: MGC | E93: Short | F93: 4472.7 | G93: 4475.3 | H93: 3 | I93: 4479.7 | K93: =IF(AND(I95<>"",J95<>"",F95<>""), (J95-F95)/(F95-I95), "") | L93: =IF(AND(F95<>"",G95<>"",I95<>""), (G95-F95)/(F95-I95), "") | M93: =IF(N95>0,"Win",IF(N95<0,"Loss","")) | N93: =IF(AND(F95<>"",G95<>"",H95<>"",D95<>""), IF(E95="Long", (G95-F95)*H95*VLOOKUP(D95,Multipliers!A:B,2,FALSE), (F95-G95)*H95*VLOOKUP(D95,Multipliers!A:B,2,FALSE)), "") | O93: =IF(AND(N95<>"",F95<>"",H95<>"",D95<>""), N95/(F95*H95*VLOOKUP(D95,Multipliers!A:B,2,FALSE)), "") | P93: =P92+N93 | Q93: Break and Retest | R93: Imported from Tradovate | S93: MGC | V93: Overtraded
A94: 101 | B94: 46265 | C94: 0.4366088 | D94: MGC | E94: Short | F94: 4472.8 | G94: 4477 | H94: 3 | I94: 4476.9 | J94: 4464.8 | K94: =IF(AND(I96<>"",J96<>"",F96<>""), (J96-F96)/(F96-I96), "") | L94: =IF(AND(F96<>"",G96<>"",I96<>""), (G96-F96)/(F96-I96), "") | M94: =IF(N96>0,"Win",IF(N96<0,"Loss","")) | N94: =IF(AND(F96<>"",G96<>"",H96<>"",D96<>""), IF(E96="Long", (G96-F96)*H96*VLOOKUP(D96,Multipliers!A:B,2,FALSE), (F96-G96)*H96*VLOOKUP(D96,Multipliers!A:B,2,FALSE)), "") | O94: =IF(AND(N96<>"",F96<>"",H96<>"",D96<>""), N96/(F96*H96*VLOOKUP(D96,Multipliers!A:B,2,FALSE)), "") | P94: =P93+N94 | Q94: Break and Retest | R94: Imported from Tradovate | S94: MGC | V94: Overtraded
A95: 102 | B95: 46265 | C95: 0.45512731 | D95: MGC | E95: Short | F95: 4483.6 | G95: 4478.2 | H95: 2 | I95: 4487.8 | J95: 4478.2 | K95: =IF(AND(I97<>"",J97<>"",F97<>""), (J97-F97)/(F97-I97), "") | L95: =IF(AND(F97<>"",G97<>"",I97<>""), (G97-F97)/(F97-I97), "") | M95: =IF(N97>0,"Win",IF(N97<0,"Loss","")) | N95: =IF(AND(F97<>"",G97<>"",H97<>"",D97<>""), IF(E97="Long", (G97-F97)*H97*VLOOKUP(D97,Multipliers!A:B,2,FALSE), (F97-G97)*H97*VLOOKUP(D97,Multipliers!A:B,2,FALSE)), "") | O95: =IF(AND(N97<>"",F97<>"",H97<>"",D97<>""), N97/(F97*H97*VLOOKUP(D97,Multipliers!A:B,2,FALSE)), "") | P95: =P94+N95 | Q95: Break and Retest | R95: Imported from Tradovate | S95: MGC | V95: Overtraded
A96: 103 | B96: 46265 | C96: 0.028159722 | D96: MGC | E96: Short | F96: 4468.2333 | G96: 4473.6 | H96: 3 | I96: 4473.5 | J96: 4467.8 | K96: =IF(AND(I96<>"",J96<>"",F96<>""), (J96-F96)/(F96-I96), "") | L96: =IF(AND(F96<>"",G96<>"",I96<>""), (G96-F96)/(F96-I96), "") | M96: =IF(N96>0,"Win",IF(N96<0,"Loss","")) | N96: =IF(AND(F96<>"",G96<>"",H96<>"",D96<>""), IF(E96="Long", (G96-F96)*H96*VLOOKUP(D96,Multipliers!A:B,2,FALSE), (F96-G96)*H96*VLOOKUP(D96,Multipliers!A:B,2,FALSE)), "") | O96: =IF(AND(N96<>"",F96<>"",H96<>"",D96<>""), N96/(F96*H96*VLOOKUP(D96,Multipliers!A:B,2,FALSE)), "") | P96: =P95+N96 | Q96: Break and Retest | R96: Imported from Tradovate | S96: MGC | V96: Overtraded
A97: 104 | B97: 46265 | C97: 0.93423611 | D97: MGC | E97: Long | F97: 4491.8 | G97: 4490.2 | H97: 1 | I97: 4490.4 | J97: 4506.4 | K97: =IF(AND(I97<>"",J97<>"",F97<>""), (J97-F97)/(F97-I97), "") | L97: =IF(AND(F97<>"",G97<>"",I97<>""), (G97-F97)/(F97-I97), "") | M97: =IF(N97>0,"Win",IF(N97<0,"Loss","")) | N97: =IF(AND(F97<>"",G97<>"",H97<>"",D97<>""), IF(E97="Long", (G97-F97)*H97*VLOOKUP(D97,Multipliers!A:B,2,FALSE), (F97-G97)*H97*VLOOKUP(D97,Multipliers!A:B,2,FALSE)), "") | O97: =IF(AND(N97<>"",F97<>"",H97<>"",D97<>""), N97/(F97*H97*VLOOKUP(D97,Multipliers!A:B,2,FALSE)), "") | P97: =P96+N97 | Q97: Break and Retest | R97: Imported from Tradovate | S97: MGC | V97: Overtraded
A98: 105 | B98: 46265 | C98: 0.9349537 | D98: MGC | E98: Long | F98: 4490.5 | G98: 4484.5 | H98: 1 | I98: 4484.5 | J98: 4506.4 | K98: =IF(AND(I98<>"",J98<>"",F98<>""), (J98-F98)/(F98-I98), "") | L98: =IF(AND(F98<>"",G98<>"",I98<>""), (G98-F98)/(F98-I98), "") | M98: =IF(N98>0,"Win",IF(N98<0,"Loss","")) | N98: =IF(AND(F98<>"",G98<>"",H98<>"",D98<>""), IF(E98="Long", (G98-F98)*H98*VLOOKUP(D98,Multipliers!A:B,2,FALSE), (F98-G98)*H98*VLOOKUP(D98,Multipliers!A:B,2,FALSE)), "") | O98: =IF(AND(N98<>"",F98<>"",H98<>"",D98<>""), N98/(F98*H98*VLOOKUP(D98,Multipliers!A:B,2,FALSE)), "") | P98: =P97+N98 | Q98: Break and Retest | R98: Imported from Tradovate | S98: MGC | V98: Revenge trade, Overtraded
A99: 106 | B99: 46265 | C99: 0.94975694 | D99: MGC | E99: Short | F99: 4481 | G99: 4487 | H99: 3 | I99: 4487 | J99: 4469 | K99: =IF(AND(I99<>"",J99<>"",F99<>""), (J99-F99)/(F99-I99), "") | L99: =IF(AND(F99<>"",G99<>"",I99<>""), (G99-F99)/(F99-I99), "") | M99: =IF(N99>0,"Win",IF(N99<0,"Loss","")) | N99: =IF(AND(F99<>"",G99<>"",H99<>"",D99<>""), IF(E99="Long", (G99-F99)*H99*VLOOKUP(D99,Multipliers!A:B,2,FALSE), (F99-G99)*H99*VLOOKUP(D99,Multipliers!A:B,2,FALSE)), "") | O99: =IF(AND(N99<>"",F99<>"",H99<>"",D99<>""), N99/(F99*H99*VLOOKUP(D99,Multipliers!A:B,2,FALSE)), "") | P99: =P98+N99 | Q99: Break and Retest | R99: Imported from Tradovate | S99: MGC | V99: Overtraded
A100: 107 | B100: 46265 | C100: 0.95883102 | D100: MGC | E100: Short | F100: 4488.4 | G100: 4484.5667 | H100: 6 | I100: 4495.2 | J100: 4483 | K100: =IF(AND(I100<>"",J100<>"",F100<>""), (J100-F100)/(F100-I100), "") | L100: =IF(AND(F100<>"",G100<>"",I100<>""), (G100-F100)/(F100-I100), "") | M100: =IF(N100>0,"Win",IF(N100<0,"Loss","")) | N100: =IF(AND(F100<>"",G100<>"",H100<>"",D100<>""), IF(E100="Long", (G100-F100)*H100*VLOOKUP(D100,Multipliers!A:B,2,FALSE), (F100-G100)*H100*VLOOKUP(D100,Multipliers!A:B,2,FALSE)), "") | O100: =IF(AND(N100<>"",F100<>"",H100<>"",D100<>""), N100/(F100*H100*VLOOKUP(D100,Multipliers!A:B,2,FALSE)), "") | P100: =P99+N100 | Q100: Break and Retest | R100: Imported from Tradovate | S100: MGC | V100: Revenge trade, Overtraded
...

Sheet Multipliers
A1: Asset | B1: Multiplier
A2: ES | B2: 50
A3: MES | B3: 5
A4: NQ | B4: 20
A5: MNQ | B5: 2
A6: YM | B6: 5
A7: RTY | B7: 50
A8: GC | B8: 100
A9: MGC | B9: 10
A10: CL | B10: 1000
A11: MCL | B11: 100
A12: QM | B12: 500
A13: MYM | B13: 0.5
A14: M2K | B14: 5

Sheet Tag Options
A1: Rules | B1: Market conditions | C1: Emotion before trade | D1: Setup | E1: Process | F1: Mistakes | G1: Learning | I1: Reference list of suggested tag values — edit freely.
A2: Followed plan | B2: Trending up | C2: Calm | D2: Break and Retest | E2: Pre-market done | F2: Revenge trade | G2: Wait for confluence
A3: Broke a rule | B3: Trending down | C3: Confident | D3: Bounce | E3: Wrote entry reason | F3: Oversized | G3: Size down on news
A4: Within daily loss limit | B4: Ranging | C4: Focused | D4: Rejection | E4: A+ process day | F4: Moved stop | G4: Let winners run
A5: Hit daily loss limit | B5: Choppy | C5: FOMO | D5: 123 Setup | E5: Cooled off between trades | F5: Cut winner early | G5: Honor the stop
A6: Within max size | B6: High volatility | C6: Fear | D6: Pivot | E6: Journaled | F6: Blew stop | G6: Trade only A+
A7: Risked >1R per trade | B7: Low volatility | C7: Greed | D7: A+ setup | E7: No pre-market | F7: No confluence | G7: Reduce overnight trading
A8: Traded planned session | B8: News day | C8: Impatient | D8: Full confluence | E8: Distracted | F8: Early entry | G8: Stick to Pullbacks
A9: Waited for A+ only | B9: Thin / overnight | C9: Frustrated | D9: Breakout | E9: Multitasking | F9: Late entry | G9: Take the 2R
A10: Stopped after 2 losses | B10: Strong trend | C10: Bored | D10: Breakdown | E10: Rushed entry | F10: Overtraded | G10: Be patient
B11: Reversal day | C11: Pressure to recover | D11: Pullback | F11: Chased entry | G11: Smaller size
C12: Tilted | D12: Reversal | F12: Out-of-plan
C13: Anxious | D13: Range fade | F13: No stop
C14: Zen mode | D14: Trend continuation
D15: VWAP bounce
D16: Support / Resistance
D17: Scalping

Sheet Trading Rules
A1: Type | B1: Rule
A2: Hard | B2: Check Economic News.
A3: Hard | B3: Mark Levels before market open. Mark the opening print as a 4/5 Level.
A4: Hard | B4: Create a plan — only long if 1H is uptrend; only short if 1H is downtrend.
A5: Hard | B5: Pick the levels you want to go long/short off based on that analysis. Label the levels AND where the analysis could switch — e.g. an uptrend holds until a level breaks; if the hourly candle closes beneath it, bias can flip down. Mark out both.
A6: Hard | B6: Trade only after 9:45. Don't trade after 12 pm.
A7: Hard | B7: Target 2–2.5 Risk to Reward.
A8: Hard | B8: Aim for 1–3 trades a day with a predefined daily stop loss and an overall assumed profit target.
A9: Other | B9: Re-taking a BR/Bounce at a level that already worked: OK, but with caution. The first Break & Retest/Bounce cleared out most of the immediate sell liquidity, so a second test at the same exact level carries higher break-through risk. Only take it if the 1H trend is still strong — otherwise size down or skip.

Sheet Analysis
A1: Overview
A2: Generated | B2: 2026-08-31 13:16
A3: Date range | B3: 2026-08-11 → 2026-08-31
A4: Trades | B4: 93
A5: Win rate | B5: 54.8%
A6: Total P&L | B6: 2383
A7: Profit factor | B7: 1.3
A8: Expectancy / trade | B8: 25.62
A9: Avg win | B9: 204.53
A10: Avg loss | B10: -191.62
A11: Avg RR targeted | B11: 1.35
A12: Avg RR realized | B12: 0.04
A13: Max drawdown | B13: -1750
A14: Max win streak | B14: 8
A15: Max loss streak | B15: 5
A17: By Setup
A18: Setup | B18: Trades | C18: Win % | D18: Total P&L | E18: Expectancy
A19: Break and Retest | B19: 88 | C19: 53% | D19: 1924 | E19: 21.86
A20: ZTH Indicator | B20: 2 | C20: 100% | D20: 351 | E20: 175.5
A21: Gap up | B21: 1 | C21: 100% | D21: 199 | E21: 199
A22: Rejection | B22: 1 | C22: 100% | D22: 134 | E22: 134
A23: Break and Retest, Rejection | B23: 1 | C23: 0% | D23: -225 | E23: -225
A25: By Instrument
A26: Instrument | B26: Trades | C26: Win % | D26: Total P&L | E26: Expectancy
A27: MGC | B27: 51 | C27: 57% | D27: 2021 | E27: 39.63
A28: MNQ | B28: 42 | C28: 52% | D28: 362 | E28: 8.62
A30: By Direction
A31: Direction | B31: Trades | C31: Win % | D31: Total P&L | E31: Expectancy
A32: Long | B32: 52 | C32: 50% | D32: 2269.5 | E32: 43.64
A33: Short | B33: 41 | C33: 61% | D33: 113.5 | E33: 2.77
A35: By Hour
A36: Hour | B36: Trades | C36: Win % | D36: Total P&L | E36: Expectancy
A37: 00:00 | B37: 4 | C37: 75% | D37: 82 | E37: 20.5
A38: 08:00 | B38: 1 | C38: 0% | D38: -57 | E38: -57
A39: 09:00 | B39: 17 | C39: 71% | D39: 1907.5 | E39: 112.21
A40: 10:00 | B40: 21 | C40: 43% | D40: 206 | E40: 9.81
A41: 11:00 | B41: 10 | C41: 40% | D41: -139 | E41: -13.9
A42: 12:00 | B42: 6 | C42: 83% | D42: -2 | E42: -0.33
A43: 13:00 | B43: 1 | C43: 0% | D43: -255 | E43: -255
A44: 14:00 | B44: 2 | C44: 0% | D44: -402 | E44: -201
A45: 15:00 | B45: 1 | C45: 0% | D45: -120 | E45: -120
A46: 18:00 | B46: 2 | C46: 100% | D46: 224 | E46: 112
A47: 19:00 | B47: 7 | C47: 57% | D47: -1470.5 | E47: -210.07
A48: 20:00 | B48: 4 | C48: 50% | D48: 457 | E48: 114.25
... A51: 23:00 | B51: 6 | C51: 50% | D51: -479 | E51: -79.83
A53: By Day of Week
A54: Day | B54: Trades | C54: Win % | D54: Total P&L | E54: Expectancy
A55: Thu | B55: 9 | C55: 56% | D55: 1387 | E55: 154.11
A56: Fri | B56: 12 | C56: 67% | D56: 930.5 | E56: 77.54
A57: Sun | B57: 9 | C57: 67% | D57: 755 | E57: 83.89
A58: Wed | B58: 25 | C58: 60% | D58: -8.5 | E58: -0.34
A59: Mon | B59: 17 | C59: 41% | D59: -256 | E59: -15.06
A60: Tue | B60: 21 | C60: 48% | D60: -425 | E60: -20.24
A62: Behavior Flags
A63: Overtrading | B63: 11 trades on 2026-08-11 (> 6)
A64: Overtrading | B64: 9 trades on 2026-08-12 (> 6)
A65: Overtrading | B65: 12 trades on 2026-08-26 (> 6)
A66: Overtrading | B66: 10 trades on 2026-08-31 (> 6)
A67: Possible revenge trade | B67: MGC Short at 08/11 19:34 — 4 min after a loss, size 10
A68: Possible revenge trade | B68: MGC Long at 08/11 23:25 — 14 min after a loss, size 10
A69: Possible revenge trade | B69: MGC Short at 08/11 23:36 — 11 min after a loss, size 20
A70: Possible revenge trade | B70: MGC Short at 08/13 22:59 — 9 min after a loss, size 3
A71: Possible revenge trade | B71: MGC Long at 08/18 10:08 — 8 min after a loss, size 3
A72: Possible revenge trade | B72: MNQ Short at 08/18 10:21 — 5 min after a loss, size 3
A73: Possible revenge trade | B73: MGC Long at 08/23 19:46 — 11 min after a loss, size 1
A74: Possible revenge trade | B74: MGC Long at 08/23 20:28 — 5 min after a loss, size 2
... A88: Negative-edge hour | B88: 19:00: 7 trades, 57% win, $-1471 total

Sheet AI Suggestions
A1: Claude AI Coaching
A3: Here's the honest read on your August data — the top-line number ($2,383 net, PF 1.3) is masking a much better trader hiding inside a much worse one. Two data cuts below explain almost the entire story.
A5: ## The core finding: your edge is real but you're diluting it 2:1
A7: Your indicator tags happen to partition all 93 trades cleanly into "quality" buckets, and the split is stark:
A9: | Quality signal | Good side | Bad side |
A10: |---|---|---|
A11: | Pullback grade | Good/A+: 34 trades → **+$5,010** | Weak/No setup: 59 trades → **-$2,627** |
A12: | 1H trend alignment | With trend: 55 trades → **+$3,787** | Against/unclear: 38 trades → **-$1,404** |
A13: | At a key level | Yes: 63 trades → **+$4,561** | No: 30 trades → **-$2,178** |
A14: | ADX (trend strength) | ≥20: 59 trades → **+$3,803** | <20 (chop): 34 trades → **-$1,420** |
A15: | Trigger-bar volume | High (≥1.2x): 34 trades → **+$2,514** | Weak: 59 trades → **-$131** |
A17: These aren't 5 different stories — they're the same story told 5 ways: **when you take an A-grade Break and Retest (at a key level, with the 1-hour trend, in a trending ADX regime, on real volume), you have a strong, repeatable edge.** When you take a low-grade version of the same setup — weak pullback, chop, against/unclear trend — you bleed. 59 of your 93 trades (63%) fell into the low-quality bucket this month. If you'd simply passed on those, you'd be sitting closer to **$5,000** net instead of $2,383, with meaningfully less drawdown and screen time. This is the single highest-leverage fix available to you — not a new setup, just stricter filtering of the one you already have.
... A36: 3. **Flag 19:00–23:00 as a reduced-size or no-trade window** unless it's an A+ setup — you have three separate hour-buckets in this window bleeding money, likely from mental fatigue or after-a-loss trading rather than genuinely bad setups at those hours.

Sheet Indicators
A1: Date | B1: Time | C1: Asset | D1: Dir | E1: P&L | F1: 1H Trend | G1: 1H ST | H1: 15m ST | I1: 5m ST | J1: 5m RSI | K1: 5m EMA | L1: 5m MACD | M1: 5m ADX | N1: 5m ATR | O1: VWAP | P1: VWAP Side | Q1: VPOC | R1: RVOL | S1: Est. Delta | T1: Fib % | U1: Fib Zone | V1: Pullback | W1: PB Score | X1: At Level | Y1: Candle | Z1: Trig Vol | AA1: STs Aligned | AB1: With 1H Trend
A2: 2026-08-11 | B2: 19:27 | C2: MGC | D2: Long | E2: 30 | F2: up | G2: down | H2: down | I2: down | J2: 53.8 | K2: bear | L2: - | M2: 17.1 | N2: 3.95 | O2: 4439.45 | P2: below | Q2: 4444.22 | R2: 2.62 | S2: -4577 | T2: 48 | U2: golden | V2: Weak | W2: 1 | X2: Round | Y2: strong bullish close | Z2: 1.78 | AA2: No | AB2: Yes
A3: 2026-08-11 | B3: 19:29 | C3: MGC | D3: Short | E3: 110 | F3: up | G3: down | H3: down | I3: down | J3: 53.8 | K3: bear | L3: - | M3: 17.1 | N3: 3.95 | O3: 4439.45 | P3: below | Q3: 4444.22 | R3: 2.62 | S3: -4577 | T3: 55 | U3: golden | V3: Weak | W3: 1 | X3: Round | Y3: strong bullish close | Z3: 1.78 | AA3: Yes | AB3: No
A4: 2026-08-11 | B4: 19:30 | C4: MGC | D4: Long | E4: -440 | F4: up | G4: down | H4: down | I4: down | J4: 45.1 | K4: bear | L4: - | M4: 17.2 | N4: 4.1 | O4: 4439.37 | P4: below | Q4: 4444.22 | R4: 1.78 | S4: -4716 | T4: 40 | U4: golden | V4: Weak | W4: 1 | X4: Round | Z4: 1.39 | AA4: No | AB4: Yes
A5: 2026-08-11 | B5: 19:34 | C5: MGC | D5: Short | E5: -1310 | F5: up | G5: down | H5: down | I5: down | J5: 45.1 | K5: bear | L5: - | M5: 17.2 | N5: 4.1 | O5: 4439.37 | P5: below | Q5: 4444.22 | R5: 1.78 | S5: -4716 | T5: 40 | U5: golden | V5: Weak | W5: 1 | X5: No | Z5: 1.39 | AA5: Yes | AB5: No
A6: 2026-08-11 | B6: 20:31 | C6: MGC | D6: Long | E6: 370 | F6: up | G6: down | H6: down | I6: up | J6: 67.4 | K6: bull | L6: + | M6: 19 | N6: 3.89 | O6: 4439.2 | P6: above | Q6: 4444.22 | R6: 1.52 | S6: -4008 | T6: 12 | U6: extended (no pullback) | V6: Weak | W6: 1 | X6: Round | Z6: 1.32 | AA6: No | AB6: Yes
A7: 2026-08-11 | B7: 21:16 | C7: MGC | D7: Long | E7: 190 | F7: up | G7: down | H7: up | I7: up | J7: 74.1 | K7: bull | L7: + | M7: 26.8 | N7: 4.03 | O7: 4439.44 | P7: above | Q7: 4444.22 | R7: 1 | S7: -2726 | T7: -18 | U7: extended (no pullback) | V7: Weak | W7: 1 | X7: No | Y7: strong bullish close | Z7: 2.38 | AA7: No | AB7: Yes
A8: 2026-08-11 | B8: 22:40 | C8: MGC | D8: Long | E8: 2160 | F8: up | G8: down | H8: up | I8: up | J8: 75.1 | K8: bull | L8: + | M8: 38 | N8: 4.31 | O8: 4441.14 | P8: above | Q8: 4444.25 | R8: 2.29 | S8: -1849 | T8: 13 | U8: extended (no pullback) | V8: Good | W8: 2 | X8: ORH/Round | Z8: 2.09 | AA8: No | AB8: Yes
A9: 2026-08-11 | B9: 23:00 | C9: MGC | D9: Long | E9: -280 | F9: up | G9: down | H9: up | I9: up | J9: 71.3 | K9: bull | L9: + | M9: 42.7 | N9: 4.49 | O9: 4442.06 | P9: above | Q9: 4440.82 | R9: 1.95 | S9: -1808 | T9: 4 | U9: extended (no pullback) | V9: Weak | W9: 1 | X9: No | Y9: strong bearish close | Z9: 1.18 | AA9: No | AB9: Yes
A10: 2026-08-11 | B10: 23:11 | C10: MGC | D10: Long | E10: -910 | F10: up | G10: down | H10: up | I10: up | J10: 68.9 | K10: bull | L10: + | M10: 44 | N10: 4.68 | O10: 4442.42 | P10: above | Q10: 4444.2 | R10: 2.07 | S10: -1900 | T10: 3 | U10: extended (no pullback) | V10: Weak | W10: 1 | X10: No | Y10: strong bearish close | Z10: 0.77 | AA10: No | AB10: Yes
A11: 2026-08-11 | B11: 23:25 | C11: MGC | D11: Long | E11: -140 | F11: up | G11: down | H11: up | I11: up | J11: 61.4 | K11: bull | L11: - | M11: 40.3 | N11: 4.37 | O11: 4442.73 | P11: above | Q11: 4444.2 | R11: 0.82 | S11: -2055 | T11: 16 | U11: shallow | V11: Weak | W11: 1 | X11: No | Z11: 0.56 | AA11: No | AB11: Yes
A12: 2026-08-11 | B12: 23:36 | C12: MGC | D12: Short | E12: 490 | F12: up | G12: down | H12: up | I12: up | J12: 55.6 | K12: bull | L12: - | M12: 37 | N12: 4.22 | O12: 4442.87 | P12: above | Q12: 4444.2 | R12: 1 | S12: -2358 | T12: -23 | U12: extended (no pullback) | V12: Weak | W12: 1 | X12: Round | Y12: strong bearish close | Z12: 0.45 | AA12: No | AB12: No
A13: 2026-08-12 | B13: 09:12 | C13: MNQ | D13: Long | E13: 47.5 | F13: up | G13: up | H13: up | I13: up | J13: 74.5 | K13: bull | L13: + | M13: 13 | N13: 29.01 | O13: 29698.51 | P13: above | Q13: 29634.79 | R13: 0.81 | S13: -20867 | T13: 5 | U13: extended (no pullback) | V13: No setup | W13: 0 | X13: No | Y13: strong bullish close | Z13: 0.65 | AA13: Yes | AB13: Yes
A14: 2026-08-12 | B14: 09:26 | C14: MGC | D14: Short | E14: 170 | F14: up | G14: up | H14: up | I14: up | J14: 48.6 | K14: bull | L14: - | M14: 14.1 | N14: 9.48 | O14: 4457.92 | P14: above | Q14: 4466.39 | R14: 1.28 | S14: 4436 | T14: 5 | U14: extended (no pullback) | V14: Good | W14: 2 | X14: Round | Y14: strong bullish close | Z14: 0.59 | AA14: No | AB14: No
A15: 2026-08-12 | B15: 09:38 | C15: MNQ | D15: Short | E15: 69.5 | F15: up | G15: up | H15: up | I15: down | J15: 49.1 | K15: bull | L15: - | M15: 15.4 | N15: 38.58 | T15: 36 | U15: shallow | V15: Good | W15: 2 | X15: Round | Z15: 4.74 | AA15: No | AB15: No
A16: 2026-08-12 | B16: 09:51 | C16: MGC | D16: Long | E16: -460 | F16: up | G16: up | H16: up | I16: up | J16: 60 | K16: bull | L16: - | M16: 14.2 | N16: 9.68 | O16: 4478.64 | P16: above | Q16: 4474.18 | R16: 1.15 | S16: 889 | T16: 20 | U16: shallow | V16: Weak | W16: 1 | X16: Round | Y16: strong bullish close | Z16: 0.7 | AA16: Yes | AB16: Yes
A17: 2026-08-12 | B17: 10:55 | C17: MNQ | D17: Long | E17: 93 | F17: up | G17: up | H17: up | I17: down | J17: 45.8 | K17: bear | L17: - | M17: 14.9 | N17: 49.91 | O17: 29904.66 | P17: below | Q17: 29878.13 | R17: 0.78 | S17: -16307 | T17: 55 | U17: golden | V17: Weak | W17: 1 | X17: PDH/ORL/Round | Z17: 0.63 | AA17: No | AB17: Yes
A18: 2026-08-12 | B18: 11:22 | C18: MNQ | D18: Long | E18: 154.5 | F18: up | G18: up | H18: up | I18: down | J18: 43.7 | K18: bear | L18: - | M18: 19.5 | N18: 45.34 | O18: 29900.13 | P18: below | Q18: 29878.13 | R18: 0.62 | S18: -16824 | T18: 59 | U18: golden | V18: Weak | W18: 1 | X18: ORL/Round | Y18: strong bearish close | Z18: 0.49 | AA18: No | AB18: Yes
A19: 2026-08-12 | B19: 11:32 | C19: MNQ | D19: Long | E19: -136.5 | F19: up | G19: up | H19: up | I19: down | J19: 42.1 | K19: bear | L19: - | M19: 21.8 | N19: 45.45 | O19: 29898.1 | P19: below | Q19: 29908.09 | R19: 0.87 | S19: -16568 | T19: 58 | U19: golden | V19: Good | W19: 2 | X19: ORL/Round | Y19: strong bearish close | Z19: 0.82 | AA19: No | AB19: Yes
A20: 2026-08-12 | B20: 11:57 | C20: MNQ | D20: Short | E20: -144 | F20: up | G20: up | H20: up | I20: down | J20: 42.8 | K20: bear | L20: - | M20: 27 | N20: 38.28 | O20: 29893.68 | P20: below | Q20: 29939.9 | R20: 0.64 | S20: -20113 | T20: 11 | U20: extended (no pullback) | V20: No setup | W20: 0 | X20: ORL/Round | Y20: strong bearish close | Z20: 0.47 | AA20: No | AB20: No
A21: 2026-08-12 | B21: 14:12 | C21: MGC | D21: Short | E21: -195 | F21: up | G21: up | H21: up | I21: down | J21: 47 | K21: bear | L21: + | M21: 22.7 | N21: 5.08 | O21: 4478.14 | P21: below | Q21: 4479.5 | R21: 0.73 | S21: -1793 | T21: 22 | U21: shallow | V21: Weak | W21: 1 | X21: No | Y21: strong bullish close | Z21: 0.39 | AA21: No | AB21: No
A22: 2026-08-13 | B22: 08:50 | C22: MGC | D22: Long | E22: -57 | F22: up | G22: down | H22: up | I22: up | J22: 61.3 | K22: bull | L22: + | M22: 26 | N22: 5.68 | O22: 4465.03 | P22: below | Q22: 4479.13 | R22: 0.63 | S22: -1051 | T22: 23 | U22: shallow | V22: Good | W22: 2 | X22: Round | Z22: 0.61 | AA22: No | AB22: Yes
A23: 2026-08-13 | B23: 09:46 | C23: MNQ | D23: Long | E23: 375 | F23: up | G23: up | H23: up | I23: up | J23: 83.7 | K23: bull | L23: + | M23: 32.8 | N23: 39.34 | O23: 29997.1 | P23: above | Q23: 29902.34 | R23: 1.08 | S23: 33183 | T23: 17 | U23: shallow | V23: Weak | W23: 1 | X23: Round | Y23: strong bullish close | Z23: 4.26 | AA23: Yes | AB23: Yes
A24: 2026-08-13 | B24: 11:24 | C24: MGC | D24: Short | E24: 285 | F24: flat | G24: down | H24: down | I24: down | J24: 41.8 | K24: bear | L24: - | M24: 29.6 | N24: 7.33 | O24: 4431.96 | P24: below | Q24: 4430.89 | R24: 1.02 | S24: 1609 | T24: 36 | U24: shallow | V24: Weak | W24: 1 | X24: ORL/Round | Y24: bullish engulfing | Z24: 0.8 | AA24: Yes | AB24: No
A25: 2026-08-13 | B25: 22:50 | C25: MGC | D25: Long | E25: -66 | F25: down | G25: down | H25: down | I25: down | J25: 39.9 | K25: bear | L25: + | M25: 52.4 | N25: 6.07 | O25: 4413.23 | P25: below | Q25: 4431.23 | R25: 0.56 | S25: -5147 | T25: 50 | U25: golden | V25: Weak | W25: 1 | X25: Round | Y25: strong bearish close | Z25: 0.31 | AA25: No | AB25: No
A26: 2026-08-13 | B26: 22:59 | C26: MGC | D26: Short | E26: -195 | F26: down | G26: down | H26: down | I26: down | J26: 39.8 | K26: bear | L26: + | M26: 52.5 | N26: 5.9 | O26: 4413.1 | P26: below | Q26: 4431.23 | R26: 1 | S26: -4987 | T26: 9 | U26: extended (no pullback) | V26: Weak | W26: 1 | X26: Round | Y26: bullish pin/hammer | Z26: 0.48 | AA26: Yes | AB26: Yes
A27: 2026-08-14 | B27: 09:47 | C27: MNQ | D27: Long | E27: 136.5 | F27: up | G27: up | H27: up | I27: down | J27: 46.8 | K27: bear | L27: - | M27: 18 | N27: 27.53 | O27: 30230.3 | P27: above | Q27: 30237.58 | R27: 0.98 | S27: 958 | T27: 43 | U27: golden | V27: Weak | W27: 1 | X27: No | Y27: strong bearish close | Z27: 4.2 | AA27: No | AB27: Yes
A28: 2026-08-14 | B28: 09:57 | C28: MNQ | D28: Long | E28: 27 | F28: up | G28: up | H28: up | I28: down | J28: 44 | K28: bear | L28: - | M28: 17 | N28: 29.86 | O28: 30231.83 | P28: below | Q28: 30229.28 | R28: 0.69 | S28: -683 | T28: 54 | U28: golden | V28: Weak | W28: 1 | X28: No | Z28: 1.7 | AA28: No | AB28: Yes
A29: 2026-08-14 | B29: 11:58 | C29: MNQ | D29: Short | E29: -162 | F29: up | G29: down | H29: down | I29: down | J29: 36.9 | K29: bear | L29: - | M29: 42.4 | N29: 32.23 | O29: 30166.81 | P29: below | Q29: 30239.55 | R29: 1.02 | S29: -24672 | T29: 17 | U29: shallow | V29: No setup | W29: 0 | X29: No | Z29: 0.68 | AA29: Yes | AB29: No
A30: 2026-08-14 | B30: 12:41 | C30: MNQ | D30: Short | E30: 27 | F30: up | G30: down | H30: down | I30: down | J30: 41.4 | K30: bear | L30: + | M30: 35 | N30: 27.31 | O30: 30155.19 | P30: below | Q30: 30239.55 | R30: 0.74 | S30: -26282 | T30: 16 | U30: shallow | V30: No setup | W30: 0 | X30: No | Y30: strong bearish close | Z30: 0.55 | AA30: Yes | AB30: No
A31: 2026-08-14 | B31: 12:46 | C31: MNQ | D31: Long | E31: 42.5 | F31: up | G31: down | H31: down | I31: down | J31: 43.5 | K31: bear | L31: + | M31: 34.7 | N31: 26.45 | O31: 30154.32 | P31: below | Q31: 30239.55 | R31: 0.74 | S31: -24705 | T31: 51 | U31: golden | V31: Good | W31: 2 | X31: No | Y31: strong bullish close | Z31: 0.57 | AA31: No | AB31: Yes
A32: 2026-08-14 | B32: 12:50 | C32: MNQ | D32: Long | E32: 35 | F32: up | G32: down | H32: down | I32: down | J32: 40.7 | K32: bear | L32: + | M32: 34.6 | N32: 25.9 | O32: 30153.37 | P32: below | Q32: 30239.55 | R32: 0.77 | S32: -25488 | T32: 55 | U32: golden | V32: Good | W32: 2 | X32: No | Z32: 0.61 | AA32: No | AB32: Yes
A33: 2026-08-17 | B33: 09:55 | C33: MNQ | D33: Long | E33: -124.5 | F33: up | G33: up | H33: down | I33: down | J33: 50.8 | K33: bear | L33: + | M33: 25.6 | N33: 32.49 | O33: 30212.46 | P33: above | Q33: 30201.93 | R33: 0.67 | S33: -9581 | T33: 15 | U33: shallow | V33: A+ | W33: 3 | X33: Round | Z33: 1.59 | AA33: No | AB33: Yes
A34: 2026-08-17 | B34: 10:09 | C34: MGC | D34: Long | E34: 240 | F34: up | G34: up | H34: up | I34: up | J34: 65.1 | K34: bull | L34: + | M34: 27.7 | N34: 6.23 | O34: 4456.81 | P34: above | Q34: 4457.35 | R34: 0.64 | S34: 604 | T34: 29 | U34: shallow | V34: Weak | W34: 1 | X34: Round | Y34: strong bearish close | Z34: 0.64 | AA34: Yes | AB34: Yes
A35: 2026-08-17 | B35: 11:51 | C35: MNQ | D35: Short | E35: 97.5 | F35: up | G35: up | H35: down | I35: up | J35: 52.5 | K35: bull | L35: - | M35: 17.1 | N35: 29.13 | O35: 30219.99 | P35: above | Q35: 30203.19 | R35: 0.94 | S35: -3153 | T35: 49 | U35: golden | V35: Good | W35: 2 | X35: Round | Y35: bullish engulfing | Z35: 0.86 | AA35: No | AB35: No
A36: 2026-08-18 | B36: 10:00 | C36: MGC | D36: Short | E36: -159 | F36: flat | G36: down | H36: down | I36: up | J36: 59.5 | K36: bull | L36: + | M36: 19.5 | N36: 7.37 | O36: 4452.11 | P36: above | Q36: 4442.54 | R36: 1.51 | S36: 5102 | T36: 53 | U36: golden | V36: Weak | W36: 1 | X36: No | Y36: strong bullish close | Z36: 2.6 | AA36: No | AB36: No
A37: 2026-08-18 | B37: 10:08 | C37: MGC | D37: Long | E37: -180 | F37: flat | G37: down | H37: down | I37: up | J37: 53.1 | K37: bull | L37: + | M37: 18.5 | N37: 7.33 | O37: 4452.43 | P37: above | Q37: 4442.54 | R37: 0.87 | S37: 4347 | T37: 27 | U37: shallow | V37: Weak | W37: 1 | X37: No | Y37: strong bearish close | Z37: 0.75 | AA37: No | AB37: No
A38: 2026-08-18 | B38: 10:16 | C38: MNQ | D38: Short | E38: -80 | F38: down | G38: down | H38: down | I38: down | J38: 38.4 | K38: bear | L38: - | M38: 11.7 | N38: 45.4 | O38: 29665.85 | P38: below | Q38: 29691.77 | R38: 1.23 | S38: -16933 | T38: 21 | U38: shallow | V38: No setup | W38: 0 | X38: ORL/Round | Y38: bullish engulfing | Z38: 1.45 | AA38: Yes | AB38: Yes
A39: 2026-08-18 | B39: 10:21 | C39: MNQ | D39: Short | E39: -295.5 | F39: down | G39: down | H39: down | I39: down | J39: 43.2 | K39: bear | L39: - | M39: 11.2 | N39: 47.03 | O39: 29663.29 | P39: below | Q39: 29691.77 | R39: 1.36 | S39: -13177 | T39: 18 | U39: shallow | V39: No setup | W39: 0 | X39: ORL/Round | Y39: strong bullish close | Z39: 1.34 | AA39: Yes | AB39: Yes
A40: 2026-08-18 | B40: 10:48 | C40: MGC | D40: Short | E40: 194 | F40: flat | G40: down | H40: down | I40: down | J40: 45 | K40: bear | L40: - | M40: 17.3 | N40: 8 | O40: 4449.98 | P40: below | Q40: 4442.54 | R40: 0.97 | S40: 2190 | T40: 35 | U40: shallow | V40: Good | W40: 2 | X40: ONL | Y40: bullish engulfing | Z40: 0.64 | AA40: Yes | AB40: No
A41: 2026-08-19 | B41: 09:43 | C41: MNQ | D41: Short | E41: 427.5 | F41: down | G41: up | H41: up | I41: down | J41: 45.8 | K41: bull | L41: - | M41: 35.4 | N41: 44.57 | O41: 29645.51 | P41: below | Q41: 29694.91 | R41: 1.38 | S41: -16404 | T41: 28 | U41: shallow | V41: Good | W41: 2 | X41: Round | Y41: strong bullish close | Z41: 3.73 | AA41: No | AB41: Yes
A42: 2026-08-19 | B42: 12:33 | C42: MNQ | D42: Short | E42: 46.5 | F42: down | G42: up | H42: down | I42: up | J42: 51.8 | K42: bull | L42: + | M42: 14 | N42: 39.1 | O42: 29547.55 | P42: above | Q42: 29591.36 | R42: 0.74 | S42: -18359 | T42: 63 | U42: deep | V42: Weak | W42: 1 | X42: Round | Y42: strong bullish close | Z42: 0.69 | AA42: No | AB42: Yes
A43: 2026-08-19 | B43: 14:34 | C43: MGC | D43: Short | E43: -207 | F43: up | G43: up | H43: up | I43: down | J43: 42.1 | K43: bear | L43: - | M43: 16.9 | N43: 5.76 | O43: 4537.69 | P43: above | Q43: 4542.69 | R43: 10.86 | S43: 7653 | T43: 34 | U43: shallow | V43: Weak | W43: 1 | X43: Round | Y43: strong bullish close | Z43: 3.11 | AA43: No | AB43: No
A44: 2026-08-19 | B44: 15:00 | C44: MNQ | D44: Short | E44: -120 | F44: down | G44: up | H44: down | I44: down | J44: 47.9 | K44: bear | L44: + | M44: 14.6 | N44: 29.18 | O44: 29547.32 | P44: below | Q44: 29545.49 | R44: 0.93 | S44: -30447 | T44: 30 | U44: shallow | V44: Weak | W44: 1 | X44: Round | Z44: 0.93 | AA44: No | AB44: Yes
A45: 2026-08-20 | B45: 09:51 | C45: MGC | D45: Long | E45: 656 | F45: up | G45: up | H45: up | I45: up | J45: 59.9 | K45: bull | L45: + | M45: 23.6 | N45: 7.27 | O45: 4535.7 | P45: above | Q45: 4535.01 | R45: 0.89 | S45: 3813 | T45: 15 | U45: extended (no pullback) | V45: Good | W45: 2 | X45: Round | Y45: strong bullish close | Z45: 0.89 | AA45: Yes | AB45: Yes
A46: 2026-08-20 | B46: 10:05 | C46: MNQ | D46: Long | E46: -25 | F46: down | G46: down | H46: up | I46: up | J46: 53.1 | K46: bull | L46: + | M46: 23.5 | N46: 54.46 | O46: 29386.98 | P46: below | Q46: 29355.18 | R46: 1.06 | S46: 16581 | T46: 61 | U46: golden | V46: Weak | W46: 1 | X46: ORL/Round | Y46: bullish engulfing | Z46: 1.51 | AA46: No | AB46: No
A47: 2026-08-21 | B47: 09:52 | C47: MGC | D47: Long | E47: 542 | F47: up | G47: up | H47: up | I47: down | J47: 47.2 | K47: bear | L47: + | M47: 22.9 | N47: 8.48 | O47: 4641.06 | P47: below | Q47: 4638.84 | R47: 1.4 | S47: 327 | T47: 39 | U47: golden | V47: Good | W47: 2 | X47: Round | Z47: 1.35 | AA47: No | AB47: Yes
A48: 2026-08-23 | B48: 19:35 | C48: MGC | D48: Long | E48: -62 | F48: up | G48: up | H48: up | I48: up | J48: 51.2 | K48: bull | L48: + | M48: 17.6 | N48: 4.28 | O48: 4670.17 | P48: below | Q48: 4673.3 | R48: 2.21 | S48: -33 | T48: 203 | U48: broke the leg (reversal risk) | V48: Weak | W48: 1 | X48: Round | Y48: strong bearish close | Z48: 1.48 | AA48: Yes | AB48: Yes
A49: 2026-08-23 | B49: 19:46 | C49: MGC | D49: Long | E49: 120 | F49: up | G49: up | H49: up | I49: up | J49: 53 | K49: bear | L49: + | M49: 15.3 | N49: 4.64 | O49: 4669.92 | P49: below | Q49: 4673.3 | R49: 1.73 | S49: -64 | T49: 253 | U49: broke the leg (reversal risk) | V49: No setup | W49: 0 | X49: Round | Y49: strong bullish close | Z49: 1.34 | AA49: Yes | AB49: Yes
A50: 2026-08-23 | B50: 20:23 | C50: MGC | D50: Long | E50: -61 | F50: up | G50: up | H50: up | I50: down | J50: 45.3 | K50: bull | L50: + | M50: 21.8 | N50: 6.88 | O50: 4678.58 | P50: below | Q50: 4690.8 | R50: 3.05 | S50: -120 | T50: 150 | U50: broke the leg (reversal risk) | V50: Weak | W50: 1 | X50: Round | Y50: strong bearish close | Z50: 2.77 | AA50: No | AB50: Yes
A51: 2026-08-23 | B51: 20:28 | C51: MGC | D51: Long | E51: 229 | F51: up | G51: up | H51: up | I51: down | J51: 39.7 | K51: bull | L51: - | M51: 22.2 | N51: 7.7 | O51: 4676.5 | P51: below | Q51: 4660.57 | R51: 3.53 | S51: -11 | V51: Weak | W51: 1 | X51: Round | Z51: 3.79 | AA51: No | AB51: Yes
A52: 2026-08-23 | B52: 22:57 | C52: MGC | D52: Long | E52: -63 | F52: up | G52: up | H52: up | I52: down | J52: 57.9 | K52: bull | L52: - | M52: 20.5 | N52: 8.43 | O52: 4683.05 | P52: below | Q52: 4689.77 | R52: 1.84 | S52: 1598 | T52: 81 | U52: broke the leg (reversal risk) | V52: Weak | W52: 1 | X52: Round | Y52: strong bullish close | Z52: 0.77 | AA52: No | AB52: Yes
A53: 2026-08-24 | B53: 00:18 | C53: MGC | D53: Long | E53: 16 | F53: up | G53: up | H53: up | I53: down | J53: 50.7 | K53: bull | L53: - | M53: 12.9 | N53: 6.23 | O53: 4684.84 | P53: above | Q53: 4689.77 | R53: 0.91 | S53: 1115 | T53: 30 | U53: shallow | V53: Weak | W53: 1 | X53: No | Y53: strong bullish close | Z53: 0.52 | AA53: No | AB53: Yes
A54: 2026-08-24 | B54: 09:39 | C54: MGC | D54: Long | E54: -120 | F54: up | G54: up | H54: up | I54: up | J54: 53.1 | K54: bull | L54: + | M54: 23.4 | N54: 8.32 | T54: 27 | U54: shallow | V54: Good | W54: 2 | X54: No | Y54: strong bearish close | Z54: 2.06 | AA54: Yes | AB54: Yes
A55: 2026-08-24 | B55: 10:58 | C55: MNQ | D55: Long | E55: -106.5 | F55: down | G55: down | H55: down | I55: down | J55: 48.6 | K55: bear | L55: + | M55: 24.6 | N55: 44.21 | O55: 29047.95 | P55: above | Q55: 29002.3 | R55: 0.83 | S55: -22834 | T55: 18 | U55: shallow | V55: Weak | W55: 1 | X55: Round | Y55: strong bearish close | Z55: 0.59 | AA55: No | AB55: No
A56: 2026-08-24 | B56: 11:13 | C56: MNQ | D56: Short | E56: -240 | F56: down | G56: down | H56: down | I56: down | J56: 43 | K56: bear | L56: + | M56: 22.1 | N56: 42.16 | O56: 29049.15 | P56: above | Q56: 29002.3 | R56: 0.82 | S56: -28614 | T56: 36 | U56: shallow | V56: Good | W56: 2 | X56: Round | Y56: strong bearish close | Z56: 0.46 | AA56: Yes | AB56: Yes
A57: 2026-08-25 | B57: 09:50 | C57: MGC | D57: Short | E57: -225 | F57: flat | G57: down | H57: down | I57: down | J57: 33.3 | K57: bear | L57: - | M57: 29.2 | N57: 8.2 | O57: 4667.74 | P57: below | Q57: 4671.26 | R57: 1.06 | S57: -1293 | T57: 10 | U57: extended (no pullback) | V57: Weak | W57: 1 | X57: ONL/Round | Y57: bearish pin | Z57: 1.36 | AA57: Yes | AB57: No
A58: 2026-08-25 | B58: 10:22 | C58: MNQ | D58: Long | E58: -90 | F58: down | G58: up | H58: down | I58: down | J58: 34.8 | K58: bear | L58: - | M58: 20.8 | N58: 41.2 | O58: 29315.54 | P58: below | Q58: 29329.98 | R58: 1.16 | S58: -11968 | V58: No setup | W58: 0 | X58: Round | Z58: 1.31 | AA58: No | AB58: No
A59: 2026-08-25 | B59: 10:32 | C59: MNQ | D59: Short | E59: 96.5 | F59: down | G59: up | H59: down | I59: down | J59: 32.1 | K59: bear | L59: - | M59: 24.2 | N59: 46.08 | O59: 29300.39 | P59: below | Q59: 29342.1 | R59: 1.76 | S59: -14734 | T59: 37 | U59: shallow | V59: Weak | W59: 1 | X59: Round | Z59: 1.96 | AA59: No | AB59: Yes
A60: 2026-08-25 | B60: 12:32 | C60: MGC | D60: Short | E60: 9 | F60: up | G60: down | H60: up | I60: up | J60: 48.3 | K60: bull | L60: - | M60: 15.2 | N60: 6.07 | O60: 4687.72 | P60: above | Q60: 4677.28 | R60: 1 | S60: 4805 | T60: 22 | U60: shallow | V60: Weak | W60: 1 | X60: Round | Y60: strong bearish close | Z60: 0.76 | AA60: No | AB60: No
A61: 2026-08-25 | B61: 23:19 | C61: MGC | D61: Short | E61: 35 | F61: up | G61: down | H61: up | I61: down | J61: 38.6 | K61: bear | L61: - | M61: 24.1 | N61: 5.11 | O61: 4698.38 | P61: above | Q61: 4701.45 | R61: 1.14 | S61: 4844 | T61: 39 | U61: golden | V61: Good | W61: 2 | X61: No | Y61: bullish pin/hammer | Z61: 0.72 | AA61: No | AB61: No
A62: 2026-08-26 | B62: 09:50 | C62: MGC | D62: Long | E62: 21 | F62: flat | G62: down | H62: down | I62: down | J62: 56.3 | K62: bull | L62: + | M62: 31.7 | N62: 7.81 | O62: 4673.72 | P62: above | Q62: 4669.87 | R62: 1 | S62: 1026 | T62: 14 | U62: extended (no pullback) | V62: Weak | W62: 1 | X62: Round | Y62: strong bearish close | Z62: 1.02 | AA62: No | AB62: No
A63: 2026-08-26 | B63: 10:18 | C63: MGC | D63: Short | E63: 96 | F63: flat | G63: down | H63: down | I63: down | J63: 53.5 | K63: bull | L63: + | M63: 24.4 | N63: 7.68 | O63: 4677.36 | P63: above | Q63: 4683.11 | R63: 0.62 | S63: 1320 | T63: 71 | U63: deep | V63: Weak | W63: 1 | X63: Round | Y63: strong bullish close | Z63: 0.48 | AA63: Yes | AB63: No
A64: 2026-08-26 | B64: 11:46 | C64: MGC | D64: Long | E64: -165 | F64: down | G64: down | H64: down | I64: down | J64: 50.7 | K64: bear | L64: + | M64: 27.1 | N64: 7.39 | O64: 4664.43 | P64: below | Q64: 4653.95 | R64: 1.4 | S64: 1914 | T64: 11 | U64: extended (no pullback) | V64: Good | W64: 2 | X64: Round | Y64: strong bullish close | Z64: 0.91 | AA64: No | AB64: No
A65: 2026-08-26 | B65: 11:55 | C65: MGC | D65: Short | E65: 185 | F65: down | G65: down | H65: down | I65: down | J65: 40 | K65: bear | L65: + | M65: 26.2 | N65: 7.62 | O65: 4664.04 | P65: below | Q65: 4653.95 | R65: 1.15 | S65: 286 | T65: 34 | U65: shallow | V65: Good | W65: 2 | X65: ONL | Y65: strong bearish close | Z65: 0.67 | AA65: Yes | AB65: Yes
A66: 2026-08-26 | B66: 13:11 | C66: MGC | D66: Short | E66: -255 | F66: down | G66: down | H66: down | I66: down | J66: 46 | K66: bear | L66: + | M66: 25.2 | N66: 5.81 | O66: 4660.62 | P66: below | Q66: 4653.95 | R66: 0.71 | S66: 1659 | T66: 21 | U66: shallow | V66: Good | W66: 2 | X66: Round | Y66: strong bullish close | Z66: 0.35 | AA66: Yes | AB66: Yes
A67: 2026-08-26 | B67: 19:54 | C67: MNQ | D67: Long | E67: 81.5 | F67: up | G67: up | H67: up | I67: up | J67: 72.6 | K67: bull | L67: - | M67: 52.8 | N67: 21.31 | O67: 29282.24 | P67: above | Q67: 29245.2 | R67: 0.97 | S67: 18909 | T67: 4 | U67: extended (no pullback) | V67: Weak | W67: 1 | X67: No | Z67: 0.74 | AA67: Yes | AB67: Yes
A68: 2026-08-26 | B68: 20:04 | C68: MNQ | D68: Long | E68: -81 | F68: up | G68: up | H68: up | I68: up | J68: 64.4 | K68: bull | L68: - | M68: 55 | N68: 23.83 | O68: 29284.88 | P68: above | Q68: 29225.22 | R68: 1.07 | S68: 18478 | T68: 11 | U68: extended (no pullback) | V68: Weak | W68: 1 | X68: No | Y68: bearish engulfing | Z68: 2.38 | AA68: Yes | AB68: Yes
A69: 2026-08-26 | B69: 21:05 | C69: MNQ | D69: Long | E69: -120 | F69: up | G69: up | H69: down | I69: down | J69: 39.8 | K69: bear | L69: - | M69: 39.3 | N69: 28.2 | O69: 29295.68 | P69: above | Q69: 29225.22 | R69: 1.59 | S69: 14973 | T69: 50 | U69: golden | V69: Good | W69: 2 | X69: No | Y69: strong bullish close | Z69: 1.01 | AA69: No | AB69: Yes
A70: 2026-08-26 | B70: 21:16 | C70: MNQ | D70: Long | E70: 302.5 | F70: up | G70: up | H70: down | I70: down | J70: 41.9 | K70: bear | L70: - | M70: 37.8 | N70: 29.85 | O70: 29296.65 | P70: above | Q70: 29225.22 | R70: 1.27 | S70: 14908 | T70: 46 | U70: golden | V70: Good | W70: 2 | X70: No | Y70: strong bullish close | Z70: 0.78 | AA70: No | AB70: Yes
A71: 2026-08-26 | B71: 21:27 | C71: MNQ | D71: Long | E71: 42 | F71: up | G71: up | H71: down | I71: down | J71: 46.9 | K71: bear | L71: - | M71: 34.6 | N71: 28.36 | O71: 29297.43 | P71: above | Q71: 29225.22 | R71: 1.16 | S71: 15841 | T71: 40 | U71: golden | V71: Good | W71: 2 | X71: Round | Z71: 0.58 | AA71: No | AB71: Yes
A72: 2026-08-26 | B72: 21:35 | C72: MNQ | D72: Long | E72: 88.5 | F72: up | G72: up | H72: down | I72: down | J72: 52.6 | K72: bear | L72: + | M72: 30.3 | N72: 27.69 | O72: 29298.41 | P72: above | Q72: 29225.22 | R72: 1.29 | S72: 16672 | T72: 37 | U72: shallow | V72: A+ | W72: 3 | X72: No | Y72: strong bullish close | Z72: 0.61 | AA72: No | AB72: Yes
A73: 2026-08-26 | B73: 22:22 | C73: MNQ | D73: Short | E73: 50 | F73: up | G73: up | H73: down | I73: up | J73: 51.9 | K73: bull | L73: + | M73: 17.3 | N73: 25.06 | O73: 29301.92 | P73: above | Q73: 29225.22 | R73: 0.49 | S73: 17858 | T73: 46 | U73: golden | V73: Weak | W73: 1 | X73: No | Z73: 0.23 | AA73: No | AB73: No
A74: 2026-08-26 | B74: 22:27 | C74: MNQ | D74: Short | E74: -46 | F74: up | G74: up | H74: down | I74: up | J74: 53.2 | K74: bull | L74: + | M74: 16.6 | N74: 24.52 | O74: 29302.09 | P74: above | Q74: 29225.22 | R74: 0.72 | S74: 18006 | T74: 46 | U74: golden | V74: Weak | W74: 1 | X74: No | Y74: bullish engulfing | Z74: 0.31 | AA74: No | AB74: No
A75: 2026-08-27 | B75: 09:43 | C75: MGC | D75: Short | E75: 360 | F75: down | G75: down | H75: down | I75: down | J75: 37.1 | K75: bear | L75: - | M75: 24.1 | N75: 6.47 | O75: 4632.83 | P75: above | Q75: 4630.68 | R75: 0.92 | S75: -2545 | T75: 40 | U75: golden | V75: Good | W75: 2 | X75: No | Z75: 1.7 | AA75: Yes | AB75: Yes
A76: 2026-08-27 | B76: 10:17 | C76: MGC | D76: Short | E76: 54 | F76: down | G76: down | H76: down | I76: down | J76: 45.9 | K76: bear | L76: - | M76: 29.6 | N76: 7.42 | O76: 4629.41 | P76: above | Q76: 4630.62 | R76: 0.78 | S76: -1296 | T76: 50 | U76: golden | V76: Good | W76: 2 | X76: No | Y76: bullish engulfing | Z76: 0.72 | AA76: Yes | AB76: Yes
A77: 2026-08-27 | B77: 20:02 | C77: MGC | D77: Short | E77: 21 | F77: down | G77: down | H77: up | I77: down | J77: 36 | K77: bear | L77: - | M77: 22.6 | N77: 3.04 | O77: 4648.88 | P77: above | Q77: 4660.41 | R77: 1.02 | S77: 2382 | T77: 25 | U77: shallow | V77: Good | W77: 2 | X77: No | Z77: 2.84 | AA77: No | AB77: Yes
A78: 2026-08-27 | B78: 21:18 | C78: MGC | D78: Short | E78: 60 | F78: down | G78: down | H78: down | I78: up | J78: 49.5 | K78: bear | L78: + | M78: 23.6 | N78: 4.77 | O78: 4648.71 | P78: below | Q78: 4660.41 | R78: 0.64 | S78: 3064 | T78: 34 | U78: shallow | V78: Good | W78: 2 | X78: ORH/Round | Z78: 1.28 | AA78: No | AB78: Yes
A79: 2026-08-28 | B79: 10:09 | C79: MGC | D79: Short | E79: 426 | F79: down | G79: down | H79: down | I79: down | J79: 27.3 | K79: bear | L79: - | M79: 22.4 | N79: 12.36 | O79: 4643.29 | P79: below | Q79: 4656.24 | R79: 9.6 | S79: -4760 | T79: 33 | U79: shallow | V79: Good | W79: 2 | X79: Round | Y79: bullish pin/hammer | Z79: 7.85 | AA79: Yes | AB79: Yes
A80: 2026-08-28 | B80: 10:25 | C80: MNQ | D80: Short | E80: 134 | F80: up | G80: up | H80: down | I80: down | J80: 54 | K80: bear | L80: - | M80: 15 | N80: 48.7 | O80: 29621.33 | P80: above | Q80: 29597.96 | R80: 1.34 | S80: -1150 | T80: 68 | U80: deep | V80: Weak | W80: 1 | X80: Round | Y80: bullish pin/hammer | Z80: 1.44 | AA80: No | AB80: No
A81: 2026-08-28 | B81: 10:40 | C81: MNQ | D81: Short | E81: -102 | F81: up | G81: up | H81: down | I81: up | J81: 64.5 | K81: bull | L81: + | M81: 16.3 | N81: 50.22 | O81: 29632.06 | P81: above | Q81: 29597.61 | R81: 1.62 | S81: 8113 | V81: No setup | W81: 0 | X81: PDH/ONH/ORH/Round | Y81: strong bullish close | Z81: 1.08 | AA81: No | AB81: No
A82: 2026-08-28 | B82: 11:12 | C82: MNQ | D82: Short | E82: -13.5 | F82: up | G82: up | H82: up | I82: up | J82: 60.4 | K82: bull | L82: + | M82: 22.7 | N82: 45.18 | O82: 29661.43 | P82: above | Q82: 29677.41 | R82: 1.4 | S82: 18971 | T82: 16 | U82: shallow | V82: No setup | W82: 0 | X82: Round | Z82: 0.62 | AA82: No | AB82: No
A83: 2026-08-28 | B83: 12:53 | C83: MNQ | D83: Long | E83: -162 | F83: flat | G83: up | H83: down | I83: down | J83: 39.7 | K83: bear | L83: - | M83: 31.6 | N83: 49.23 | O83: 29635.25 | P83: below | Q83: 29651.01 | R83: 1.57 | S83: -23005 | T83: 14 | U83: extended (no pullback) | V83: No setup | W83: 0 | X83: Round | Y83: strong bearish close | Z83: 0.67 | AA83: No | AB83: No
A84: 2026-08-30 | B84: 18:03 | C84: MGC | D84: Long | E84: 199 | F84: down | G84: down | H84: down | I84: up | J84: 66.1 | K84: bull | L84: + | M84: 41.8 | N84: 6.92 | T84: 87 | U84: broke the leg (reversal risk) | V84: Weak | W84: 1 | X84: Round | Y84: strong bullish close | Z84: 0.75 | AA84: No | AB84: No
A85: 2026-08-30 | B85: 18:28 | C85: MGC | D85: Short | E85: 25 | F85: down | G85: down | H85: down | I85: up | J85: 48.3 | K85: bull | L85: + | M85: 37.9 | N85: 7.97 | O85: 4510.46 | P85: below | Q85: 4511.4 | R85: 5.83 | S85: -230 | T85: 32 | U85: shallow | V85: Good | W85: 2 | X85: Round | Y85: bearish engulfing | Z85: 2.31 | AA85: No | AB85: Yes
A86: 2026-08-30 | B86: 21:25 | C86: MGC | D86: Short | E86: 42 | F86: down | G86: down | H86: down | I86: down | J86: 41.9 | K86: bear | L86: - | M86: 18.1 | N86: 9.27 | O86: 4504.89 | P86: below | Q86: 4500.17 | R86: 1 | S86: 2081 | T86: 23 | U86: shallow | V86: No setup | W86: 0 | X86: Round | Y86: strong bearish close | Z86: 0.58 | AA86: Yes | AB86: Yes
A87: 2026-08-30 | B87: 23:30 | C87: MGC | D87: Short | E87: 326 | F87: down | G87: down | H87: down | I87: up | J87: 45.5 | K87: bear | L87: + | M87: 27.4 | N87: 8.07 | O87: 4489.69 | P87: below | Q87: 4478.81 | R87: 1.42 | S87: -1099 | T87: 36 | U87: shallow | V87: Good | W87: 2 | X87: Round | Y87: strong bearish close | Z87: 0.38 | AA87: No | AB87: Yes
A88: 2026-08-31 | B88: 00:07 | C88: MGC | D88: Short | E88: 47 | F88: down | G88: down | H88: down | I88: up | J88: 41.8 | K88: bear | L88: + | M88: 23.8 | N88: 6.17 | O88: 4489 | P88: below | Q88: 4478.81 | R88: 1.17 | S88: -1597 | T88: 30 | U88: shallow | V88: Weak | W88: 1 | X88: Round | Z88: 0.44 | AA88: No | AB88: Yes
A89: 2026-08-31 | B89: 00:11 | C89: MGC | D89: Long | E89: 46 | F89: down | G89: down | H89: down | I89: up | J89: 45.5 | K89: bear | L89: + | M89: 23.1 | N89: 6.15 | O89: 4488.63 | P89: below | Q89: 4478.81 | R89: 3.96 | S89: -1154 | T89: 44 | U89: golden | V89: Weak | W89: 1 | X89: No | Y89: bullish engulfing | Z89: 1.38 | AA89: No | AB89: No
A90: 2026-08-31 | B90: 00:40 | C90: MGC | D90: Short | E90: -161 | F90: down | G90: down | H90: down | I90: up | J90: 46.3 | K90: bear | L90: + | M90: 19.3 | N90: 5.48 | O90: 4487.97 | P90: below | Q90: 4478.81 | R90: 0.95 | S90: -719 | T90: 30 | U90: shallow | V90: Weak | W90: 1 | X90: Round | Y90: bullish pin/hammer | Z90: 0.46 | AA90: No | AB90: Yes
A91: 2026-08-31 | B91: 09:42 | C91: MNQ | D91: Short | E91: 134 | F91: down | G91: down | H91: down | I91: up | J91: 45.7 | K91: bear | L91: + | M91: 20.5 | N91: 32.05 | O91: 29437.45 | P91: below | Q91: 29467.73 | R91: 0.89 | S91: -14014 | T91: 31 | U91: shallow | V91: A+ | W91: 3 | X91: PDL | Z91: 4.01 | AA91: No | AB91: Yes
A92: 2026-08-31 | B92: 09:56 | C92: MNQ | D92: Long | E92: -129 | F92: down | G92: down | H92: down | I92: up | J92: 52.3 | K92: bull | L92: + | M92: 24.9 | N92: 38.19 | O92: 29438.41 | P92: above | Q92: 29466.76 | R92: 0.74 | S92: -8579 | T92: 40 | U92: golden | V92: Good | W92: 2 | X92: Round | Y92: strong bearish close | Z92: 1.68 | AA92: No | AB92: No
A93: 2026-08-31 | B93: 10:01 | C93: MGC | D93: Short | E93: -78 | F93: down | G93: down | H93: down | I93: down | J93: 28.2 | K93: bear | L93: - | M93: 32.7 | N93: 6.62 | O93: 4479.19 | P93: below | Q93: 4470.81 | R93: 0.83 | S93: -5090 | T93: 13 | U93: extended (no pullback) | V93: Weak | W93: 1 | X93: Round | Z93: 1.38 | AA93: Yes | AB93: Yes
A94: 2026-08-31 | B94: 10:11 | C94: MNQ | D94: Short | E94: -120 | F94: down | G94: down | H94: down | I94: down | J94: 44.6 | K94: bear | L94: - | M94: 22.4 | N94: 39.3 | O94: 29430.09 | P94: below | Q94: 29467.56 | R94: 0.79 | S94: -18379 | T94: 16 | U94: shallow | V94: A+ | W94: 3 | X94: ORL/Round | Z94: 1.19 | AA94: Yes | AB94: Yes
A95: 2026-08-31 | B95: 10:28 | C95: MGC | D95: Short | E95: -126 | F95: down | G95: down | H95: down | I95: down | J95: 32.8 | K95: bear | L95: - | M95: 33.9 | N95: 6.89 | O95: 4477.82 | P95: below | Q95: 4470.81 | R95: 0.7 | S95: -4540 | T95: 13 | U95: extended (no pullback) | V95: Weak | W95: 1 | X95: Round | Z95: 0.56 | AA95: Yes | AB95: Yes
A96: 2026-08-31 | B96: 10:41 | C96: MNQ | D96: Long | E96: 250 | F96: down | G96: down | H96: down | I96: down | J96: 52.5 | K96: bear | L96: + | M96: 19.4 | N96: 40.2 | O96: 29420.42 | P96: below | Q96: 29429.81 | R96: 0.98 | S96: -15436 | T96: 31 | U96: shallow | V96: Good | W96: 2 | X96: Round | Z96: 0.83 | AA96: No | AB96: No
A97: 2026-08-31 | B97: 10:47 | C97: MNQ | D97: Long | E97: -87.5 | F97: down | G97: down | H97: down | I97: down | J97: 46.3 | K97: bear | L97: + | M97: 19 | N97: 40.48 | O97: 29419.96 | P97: below | Q97: 29429.81 | R97: 0.8 | S97: -18500 | T97: 33 | U97: shallow | V97: Good | W97: 2 | X97: Round | Y97: bearish engulfing | Z97: 0.68 | AA97: No | AB97: No
A98: 2026-08-31 | B98: 10:48 | C98: MNQ | D98: Long | E98: -57 | F98: down | G98: down | H98: down | I98: down | J98: 46.3 | K98: bear | L98: + | M98: 19 | N98: 40.48 | O98: 29419.96 | P98: below | Q98: 29429.81 | R98: 0.8 | S98: -18500 | T98: 42 | U98: golden | V98: Good | W98: 2 | X98: ORL/Round | Y98: bearish engulfing | Z98: 0.68 | AA98: No | AB98: No
A99: 2026-08-31 | B99: 10:55 | C99: MGC | D99: Short | E99: 108 | F99: down | G99: down | H99: down | I99: down | J99: 47.9 | K99: bear | L99: + | M99: 25 | N99: 7.13 | O99: 4478.31 | P99: above | Q99: 4474.83 | R99: 0.99 | S99: -4347 | T99: 36 | U99: shallow | V99: Good | W99: 2 | X99: No | Y99: bearish pin | Z99: 0.71 | AA99: Yes | AB99: Yes
A100: 2026-08-31 | B100: 22:25 | C100: MGC | D100: Long | E100: -16 | F100: down | G100: down | H100: up | I100: down | J100: 41.4 | K100: bear | L100: - | M100: 15.5 | N100: 4.68 | O100: 4484.98 | P100: above | Q100: 4481.28 | R100: 0.78 | S100: -7255 | T100: 49 | U100: golden | V100: Weak | W100: 1 | X100: Round | Y100: strong bearish close | Z100: 0.7 | AA100: No | AB100: No
...

Sheet Economic News
A1: Date | B1: Time (ET) | C1: Currency | D1: Impact | E1: Event | F1: Actual | G1: Forecast | H1: Previous
A2: 2026-08-13 | B2: 08:30 | C2: USD | D2: High | E2: CPI | F2: 0.2% | G2: 0.2% | H2: 0.0%
A3: 2026-08-14 | B3: 08:30 | C3: USD | D3: High | E3: PPI | F3: 0.2% | G3: 0.3% | H3: 0.4%
A4: 2026-08-15 | B4: 08:30 | C4: USD | D4: High | E4: Retail Sales | F4: -0.3% | G4: 0.2% | H4: -0.2%
A5: 2026-08-20 | B5: 14:00 | C5: USD | D5: High | E5: FOMC Minutes
A6: 2026-08-27 | B6: 08:30 | C6: USD | D6: High | E6: PCE | F6: 0.2% | G6: 0.2% | H6: 0.1%
A7: 2026-08-27 | B7: 08:30 | C7: USD | D7: High | E7: GDP | F7: 1.5% | G7: 1.5% | H7: 2.1%
A8: 2026-08-29 | B8: 10:00 | C8: USD | D8: High | E8: Fed Chair Speaks
A9: 2026-08-29 | B9: 10:00 | C9: USD | D9: High | E9: Payrolls | F9: -79.00K | H9: -862.00K
